Workbook

Sheet OVERVIEW
B1: 🎯 JD-TO-RESUME MATCHING UTILITY
B2: Automated Job Description analysis across 3 professional tracks
B3: AI Transformation • Technical Program Manager • IT Delivery • Product Manager
B5: 🚀 QUICK START — 3 Steps to Get Started
B6: STEP 1 | C6: STEP 2 | D6: STEP 3
B7: 📋 Go to JD_INPUT | C7: 📝 Paste JD into B10 | D7: 🎯 See Best Fit at Row 25
B8: =HYPERLINK("#JD_INPUT!A1","→ Open JD_INPUT sheet") -> → Open JD_INPUT sheet | C8: Ctrl+V works instantly — no manual entry required | D8: Score, keywords, bullets all auto-populate
B10: 🧭 NAVIGATE THE UTILITY — Click any card to jump to that sheet
B11: 📋 | C11: 🤖 | D11: ⚙️
B12: =HYPERLINK("#JD_INPUT!A1","JD_INPUT") -> JD_INPUT | C12: =HYPERLINK("#AI_SCORE!A1","AI_SCORE") -> AI_SCORE | D12: =HYPERLINK("#TPM_SCORE!A1","TPM_SCORE") -> TPM_SCORE
B13: Paste JD • See scores • Get recommendations | C13: AI Transformation Manager scoring engine | D13: Technical Program Manager scoring engine
B15: 🛠️ | C15: 🔑 | D15: 🏆
B16: =HYPERLINK("#ITDM_SCORE!A1","ITDM_SCORE") -> ITDM_SCORE | C16: =HYPERLINK("#KEYWORDS!A1","KEYWORDS") -> KEYWORDS | D16: =HYPERLINK("#FINAL_RECOMMENDATION!A1","FINAL_RECOMMENDATION") -> FINAL_RECOMMENDATION
B17: IT Delivery Manager scoring engine | C17: 45 keyword synonyms • Tier & Track tagged | D17: Final report • Radar chart • Cover letter picker
B19: ✍️ | C19: 💡
B20: =HYPERLINK("#BULLET_GENERATOR!A1","BULLET_GENERATOR") -> BULLET_GENERATOR | C20: PRO TIPS
B21: 45 pre-written resume bullets — copy-ready | C21: Score ≥32 = Strong Match • 25-31 = Good • 18-24 = Moderate • <18 = Skip
B23: 📊 SCORING KEY — Understand the numbers
B24: 🟢 STRONG MATCH | C24: 🔵 GOOD MATCH | D24: 🟡 MODERATE MATCH
B25: Score ≥ 32 | C25: Score 25 – 31 | D25: Score 18 – 24
B26: Apply with confidence | C26: Tailor a few bullets, then apply | D26: Significant tailoring needed
B28: 📎 RESOURCES — Resume & Cover Letter Templates
B29: AI Transformation | C29: Technical Program Mgr | D29: IT Delivery Manager | E29: Product Manager
B30: =HYPERLINK("https://www.genspark.ai/api/files/s/QUBpsO27r","📄 Download Resume") -> 📄 Download Resume | C30: =HYPERLINK("https://www.genspark.ai/api/files/s/BLpvZjmUt","📄 Download Resume") -> 📄 Download Resume | D30: =HYPERLINK("https://www.genspark.ai/api/files/s/kaZPyfr7","📄 Download Resume") -> 📄 Download Resume | E30: Resume - (Template TBD)
B31: =HYPERLINK("https://www.genspark.ai/api/files/s/lkUPzCNe","✉️ Cover Letter") -> ✉️ Cover Letter | C31: =HYPERLINK("https://www.genspark.ai/api/files/s/PxGCoBuk","✉️ Cover Letter") -> ✉️ Cover Letter | D31: =HYPERLINK("https://www.genspark.ai/api/files/s/lPnFfxiB","✉️ Cover Letter") -> ✉️ Cover Letter | E31: Cover Letter - (Template TBD)
E32: PM_SCORE & Bullets 49-63
B33: ⚡ Auto-scoring active — Paste JD in JD_INPUT!B10 and everything updates instantly
B34: Version 2.0 • 8 sheets • 45 keywords • 60 bullet templates • Radar & Bar charts

Sheet JD_INPUT
A1: Job Description Input
A9: PASTE JOB DESCRIPTION HERE
A10: PASTE FULL JD INTO CELL B10 | B10: About The Job The Field Platforms Operations Lead role is a part of the Go-to-Market Capabilities (GTMC), Customer Facing Capabilities (CFC), CRM & Enablers team. The GTMC organization drives best-in-class capabilities and brings value and excellence in commercial operations. The GTMC organization is a key part of the modernization of Sanofi and allows all business operations efforts to be focused on Sanofi "Take the Lead" priorities across products, markets, and pipelines. It accomplishes these goals through realizing the efficiencies of removing silos that exist between our business units, avoiding the duplication and overlapping of resources, standardizing our processes and tools, operating with a One Sanofi approach to accelerate our key capabilities development, and fostering the entrepreneurial spirit by speeding up the decision making process. This role serves as the technical authority for OneCRM US field platform operations, leading the strategic vision for CRM operations, data governance, and platform evolution. This leader designs and implements scalable operational solutions that support multi-brand, multi-market launch requirements, ensuring enterprise-wide CRM performance, data integrity, and continuous platform transformation. This position will work closely with CRM & Enablers Team members in the US, US-based stakeholders, Hyderabad HUB resources, contracted system enhancement resources, Sr. Field Management, the Workday Team, select vendors (i.e. Hibbert), other GTMC pillars, Veeva, and Sanofi Digital to lead the end-to-end design, governance, and evolution of OneCRM US field platform operations. This leader serves as a strategic partner across the OneCRM US ecosystem, influencing platform direction, data governance standards, and operational frameworks that underpin enterprise-wide CRM performance. Main Responsibilities Lead the strategic vision and operational roadmap for OneCRM US field platform operations, ensuring alignment with enterprise CRM standards and business priorities Influence platform strategy and technical architecture decisions across OneCRM US, shaping long-term CRM evolution and downstream system integration Serve as the technical authority for CRM data governance, establishing standards, policies, and frameworks that ensure data integrity across the OneCRM US ecosystem Drive enterprise-wide data governance initiatives, influencing data quality standards across multiple business units and downstream systems Design and implement scalable CRM operational solutions that support multi-brand, multi-market launch requirements across the OneCRM US ecosystem Architect end-to-end operational frameworks and processes that scale with organizational growth and platform evolution Lead and mentor the field platforms operations team, providing technical guidance, knowledge transfer, and career development support Drive capability building across the broader CRM operations community through structured knowledge sharing and best practice development Partner with Platform, Digital, and Business teams to influence technical decisions on incoming platform requests and CRM enhancements Influence senior stakeholder priorities and resource strategies across multiple concurrent launch projects and business units Lead transformation of CRM operational processes, driving adoption of modern approaches and establishing performance measurement frameworks Investigate and remediate escalated inquiries, applying technical expertise to resolve complex issues and prevent recurrence through systemic process improvements Drive cross-functional collaboration across partner GTMC US teams, ensuring operational strategies are integrated with platform and business initiatives About Our Team The CRM & Enablers Team is a part of the GTMC organization in the US. The CRM & Enablers Team strives to support our business customer facing teams by delivering innovative CRM capabilities that are timely, reliable, accurate, and constantly improving. We focus on our customers — both brand teams and customer facing teams — to adapt our CRM platform and operational systems to meet their needs. Our efforts to streamline and maintain OneCRM US bring value and impact to the organization by reducing the manual workload on our customer facing teams, by providing accurate activity data back to reporting systems, and acting as the nexus of data flow to and from Sanofi data systems. This team operates as a strategic partner to the business, driving platform excellence and enabling field force effectiveness at enterprise scale About The Candidate This candidate has a demonstrated track record of leading technical teams, influencing enterprise platform strategy, and designing scalable operational solutions across multiple business units and product launches. They bring deep expertise in CRM operations, data governance, and field platform management, combined with the ability to translate complex technical requirements into enterprise-wide operational frameworks. This leader has experience architecting CRM solutions, driving process transformation, and building organizational capability at scale. They are skilled at influencing senior stakeholders, navigating complex matrix environments, and shaping platform strategy across concurrent launch programs. Strong English communication skills and availability to engage with US stakeholders with significant operational hour overlap are essential. Ideal Experience Bachelor's degree from an accredited four-year college or university (Project Management Masters or MBA preferred) 7+ years of progressive CRM operations and field platform experience with demonstrated leadership 7+ years of experience in Biotechnology or Pharmaceuticals Proven track record of leading technical teams and driving strategic operational initiatives across enterprise-scale programs Experience in solution architecture for CRM platforms and operational frameworks Advanced expertise in data governance, data quality standards, and enterprise data management Advanced skills in managing senior stakeholder relationships across business units and multiple launch projects Experience influencing enterprise-wide platform strategy and operational approaches Strong knowledge and experience with Veeva CRM, Agile processes, and field force management systems A keen eye for improvement opportunities and the demonstrated ability to deliver on these opportunities Clear communication skills with the ability to explain not only the requirements and the "ask", but also the "why" with credibility Motivated, energetic, and a respected contributor who engages and elevates others Ability to change behaviors to evolve to the company's strategies and initiatives Experience working and thriving in a matrix environment Strong English communication skills with the ability to engage and align diverse stakeholders across geographies and functions
B12: =LOWER(B10) -> about the job the field platforms operations lead role is a part of the go-to-market capabilities (gtmc), customer facing capabilities (cfc), crm & enablers team. the gtmc organization drives best-in-class capabilities and brings value and excellence in commercial operations. the gtmc organization is a key part of the modernization of sanofi and allows all business operations efforts to be focused on sanofi "take the lead" priorities across products, markets, and pipelines. it accomplishes these goals through realizing the efficiencies of removing silos that exist between our business units, avoiding the duplication and overlapping of resources, standardizing our processes and tools, operating with a one sanofi approach to accelerate our key capabilities development, and fostering the entrepreneurial spirit by speeding up the decision making process. this role serves as the technical authority for onecrm us field platform operations, leading the strategic vision for crm operations, data governance, and platform evolution. this leader designs and implements scalable operational solutions that support multi-brand, multi-market launch requirements, ensuring enterprise-wide crm performance, data integrity, and continuous platform transformation. this position will work closely with crm & enablers team members in the us, us-based stakeholders, hyderabad hub resources, contracted system enhancement resources, sr. field management, the workday team, select vendors (i.e. hibbert), other gtmc pillars, veeva, and sanofi digital to lead the end-to-end design, governance, and evolution of onecrm us field platform operations. this leader serves as a strategic partner across the onecrm us ecosystem, influencing platform direction, data governance standards, and operational frameworks that underpin enterprise-wide crm performance. main responsibilities lead the strategic vision and operational roadmap for onecrm us field platform operations, ensuring alignment with enterprise crm standards and business priorities influence platform strategy and technical architecture decisions across onecrm us, shaping long-term crm evolution and downstream system integration serve as the technical authority for crm data governance, establishing standards, policies, and frameworks that ensure data integrity across the onecrm us ecosystem drive enterprise-wide data governance initiatives, influencing data quality standards across multiple business units and downstream systems design and implement scalable crm operational solutions that support multi-brand, multi-market launch requirements across the onecrm us ecosystem architect end-to-end operational frameworks and processes that scale with organizational growth and platform evolution lead and mentor the field platforms operations team, providing technical guidance, knowledge transfer, and career development support drive capability building across the broader crm operations community through structured knowledge sharing and best practice development partner with platform, digital, and business teams to influence technical decisions on incoming platform requests and crm enhancements influence senior stakeholder priorities and resource strategies across multiple concurrent launch projects and business units lead transformation of crm operational processes, driving adoption of modern approaches and establishing performance measurement frameworks investigate and remediate escalated inquiries, applying technical expertise to resolve complex issues and prevent recurrence through systemic process improvements drive cross-functional collaboration across partner gtmc us teams, ensuring operational strategies are integrated with platform and business initiatives about our team the crm & enablers team is a part of the gtmc organization in the us. the crm & enablers team strives to support our business customer facing teams by delivering innovative crm capabilities that are timely, reliable, accurate, and constantly improving. we focus on our customers — both brand teams and customer facing teams — to adapt our crm platform and operational systems to meet their needs. our efforts to streamline and maintain onecrm us bring value and impact to the organization by reducing the manual workload on our customer facing teams, by providing accurate activity data back to reporting systems, and acting as the nexus of data flow to and from sanofi data systems. this team operates as a strategic partner to the business, driving platform excellence and enabling field force effectiveness at enterprise scale about the candidate this candidate has a demonstrated track record of leading technical teams, influencing enterprise platform strategy, and designing scalable operational solutions across multiple business units and product launches. they bring deep expertise in crm operations, data governance, and field platform management, combined with the ability to translate complex technical requirements into enterprise-wide operational frameworks. this leader has experience architecting crm solutions, driving process transformation, and building organizational capability at scale. they are skilled at influencing senior stakeholders, navigating complex matrix environments, and shaping platform strategy across concurrent launch programs. strong english communication skills and availability to engage with us stakeholders with significant operational hour overlap are essential. ideal experience bachelor's degree from an accredited four-year college or university (project management masters or mba preferred) 7+ years of progressive crm operations and field platform experience with demonstrated leadership 7+ years of experience in biotechnology or pharmaceuticals proven track record of leading technical teams and driving strategic operational initiatives across enterprise-scale programs experience in solution architecture for crm platforms and operational frameworks advanced expertise in data governance, data quality standards, and enterprise data management advanced skills in managing senior stakeholder relationships across business units and multiple launch projects experience influencing enterprise-wide platform strategy and operational approaches strong knowledge and experience with veeva crm, agile processes, and field force management systems a keen eye for improvement opportunities and the demonstrated ability to deliver on these opportunities clear communication skills with the ability to explain not only the requirements and the "ask", but also the "why" with credibility motivated, energetic, and a respected contributor who engages and elevates others ability to change behaviors to evolve to the company's strategies and initiatives experience working and thriving in a matrix environment strong english communication skills with the ability to engage and align diverse stakeholders across geographies and functions
A14: 🚀 GET FINAL SUGGESTION ➜ (Auto-processes when JD is pasted into B10)
A15: =IF(LEN(B10)<50,"⚠️ Paste a Job Description into cell B10 above (minimum 50 characters). Auto-processing will start immediately.","✅ JD PROCESSED — "&LEN(B10)&" characters analyzed. See Final Recommendation below ↓") -> ✅ JD PROCESSED — 6943 characters analyzed. See Final Recommendation below ↓
A17: 🔍 AUTO-PARSED JD INSIGHTS
A18: 📊 Seniority Level Detected | B18: =IF(LEN(B10)<50,"—",IF(OR(ISNUMBER(SEARCH("chief",B12)),ISNUMBER(SEARCH("cto",B12)),ISNUMBER(SEARCH("cio",B12)),ISNUMBER(SEARCH("cdo",B12))),"C-Suite / Chief",IF(OR(ISNUMBER(SEARCH("svp",B12)),ISNUMBER(SEARCH("evp",B12)),ISNUMBER(SEARCH("senior vice president",B12)),ISNUMBER(SEARCH("executive vice president",B12))),"SVP / EVP",IF(OR(ISNUMBER(SEARCH("vice president",B12)),ISNUMBER(SEARCH(" vp ",B12)),ISNUMBER(SEARCH("vp of",B12))),"VP",IF(OR(ISNUMBER(SEARCH("senior director",B12)),ISNUMBER(SEARCH("sr. director",B12)),ISNUMBER(SEARCH("sr director",B12))),"Senior Director",IF(OR(ISNUMBER(SEARCH("head of",B12)),ISNUMBER(SEARCH("director",B12))),"Director / Head",IF(OR(ISNUMBER(SEARCH("principal",B12)),ISNUMBER(SEARCH("staff ",B12)),ISNUMBER(SEARCH("distinguished",B12))),"Principal / Staff",IF(OR(ISNUMBER(SEARCH("senior manager",B12)),ISNUMBER(SEARCH("sr manager",B12)),ISNUMBER(SEARCH("sr. manager",B12))),"Senior Manager",IF(OR(ISNUMBER(SEARCH("manager",B12)),ISNUMBER(SEARCH("lead ",B12))),"Manager / Lead","Individual Contributor / Not detected"))))))))) -> Manager / Lead
A19: 💰 Salary Range (parsed) | B19: =IF(LEN(B10)<50,"—",IF(ISNUMBER(SEARCH("$",B10)),"Salary mentioned in JD — scan for $ figures",IF(OR(ISNUMBER(SEARCH("compensation",B12)),ISNUMBER(SEARCH("salary",B12)),ISNUMBER(SEARCH("pay range",B12)),ISNUMBER(SEARCH("base pay",B12))),"Compensation referenced (no explicit $ figure)","Not specified in JD"))) -> Not specified in JD
A20: 📍 Work Location / Mode | B20: =IF(LEN(B10)<50,"—",IF(ISNUMBER(SEARCH("remote",B12)),IF(ISNUMBER(SEARCH("hybrid",B12)),"Hybrid (Remote + Onsite)",IF(ISNUMBER(SEARCH("fully remote",B12)),"Fully Remote","Remote friendly")),IF(ISNUMBER(SEARCH("hybrid",B12)),"Hybrid",IF(OR(ISNUMBER(SEARCH("onsite",B12)),ISNUMBER(SEARCH("on-site",B12)),ISNUMBER(SEARCH("in-office",B12)),ISNUMBER(SEARCH("in office",B12))),"Onsite / In-office",IF(B5<>"",B5,"Not specified"))))) -> Not specified
A21: 🕐 Employment Type | B21: =IF(LEN(B10)<50,"—",IF(OR(ISNUMBER(SEARCH("contract",B12)),ISNUMBER(SEARCH("contractor",B12)),ISNUMBER(SEARCH("c2c",B12)),ISNUMBER(SEARCH("w2 contract",B12))),"Contract / C2C",IF(OR(ISNUMBER(SEARCH("part-time",B12)),ISNUMBER(SEARCH("part time",B12))),"Part-Time",IF(OR(ISNUMBER(SEARCH("intern",B12)),ISNUMBER(SEARCH("internship",B12))),"Internship",IF(OR(ISNUMBER(SEARCH("full-time",B12)),ISNUMBER(SEARCH("full time",B12)),ISNUMBER(SEARCH("permanent",B12))),"Full-Time / Permanent","Full-Time (assumed)"))))) -> Contract / C2C
A22: 🏢 Industry Signals | B22: =IF(LEN(B10)<50,"—",TRIM(IF(OR(ISNUMBER(SEARCH("banking",B12)),ISNUMBER(SEARCH("financial services",B12)),ISNUMBER(SEARCH("fintech",B12)),ISNUMBER(SEARCH("insurance",B12))),"Financial Services ","")&IF(OR(ISNUMBER(SEARCH("healthcare",B12)),ISNUMBER(SEARCH("pharma",B12)),ISNUMBER(SEARCH("life sciences",B12))),"Healthcare/Pharma ","")&IF(OR(ISNUMBER(SEARCH("retail",B12)),ISNUMBER(SEARCH("e-commerce",B12)),ISNUMBER(SEARCH("ecommerce",B12))),"Retail/E-commerce ","")&IF(OR(ISNUMBER(SEARCH("manufacturing",B12)),ISNUMBER(SEARCH("industrial",B12))),"Manufacturing ","")&IF(OR(ISNUMBER(SEARCH("consulting",B12)),ISNUMBER(SEARCH("advisory",B12))),"Consulting ","")&IF(OR(ISNUMBER(SEARCH("technology",B12)),ISNUMBER(SEARCH("saas",B12)),ISNUMBER(SEARCH("software",B12))),"Technology/SaaS ",""))) -> Healthcare/Pharma Technology/SaaS
A24: 🏆 FINAL RECOMMENDATION (auto-updates when JD is pasted)
A25: 🎯 BEST-FIT RESUME | B25: =IF(LEN(B10)<50,"⏳ Waiting for JD input...",INDEX({"AI Transformation Manager","Technical Program Manager","IT Delivery Manager","Product Manager"},MATCH(MAX(AI_SCORE!D26,TPM_SCORE!D26,ITDM_SCORE!D26,PM_SCORE!D26),CHOOSE({1;2;3;4},AI_SCORE!D26,TPM_SCORE!D26,ITDM_SCORE!D26,PM_SCORE!D26),0))) -> Technical Program Manager
A26: 📈 Best Score & Match Level | B26: =IF(LEN(B10)<50,"—",MAX(AI_SCORE!D26,TPM_SCORE!D26,ITDM_SCORE!D26,PM_SCORE!D26)&" points → "&IF(MAX(AI_SCORE!D26,TPM_SCORE!D26,ITDM_SCORE!D26,PM_SCORE!D26)>=32,"🟢 STRONG MATCH — Apply with confidence",IF(MAX(AI_SCORE!D26,TPM_SCORE!D26,ITDM_SCORE!D26,PM_SCORE!D26)>=25,"🔵 GOOD MATCH — Tailor a few bullets",IF(MAX(AI_SCORE!D26,TPM_SCORE!D26,ITDM_SCORE!D26,PM_SCORE!D26)>=18,"🟡 MODERATE MATCH — Significant tailoring needed","🔴 WEAK MATCH — Reposition heavily or skip")))) -> 22 points → 🟡 MODERATE MATCH — Significant tailoring needed
A27: 📄 Recommended Cover Letter | B27: =IF(LEN(B10)<50,"—",IF(B25="AI Transformation Manager","Use AI Transformation Manager Cover Letter → https://www.genspark.ai/api/files/s/lkUPzCNe",IF(B25="Technical Program Manager","Use Technical Program Manager Cover Letter → https://www.genspark.ai/api/files/s/PxGCoBuk",IF(B25="IT Delivery Manager","Use IT Delivery Manager Cover Letter → https://www.genspark.ai/api/files/s/lPnFfxiB","Use Product Manager Cover Letter → (Template TBD)")))) -> Use Technical Program Manager Cover Letter → https://www.genspark.ai/api/files/s/PxGCoBuk
A28: 🎬 Top Action Before Applying | B28: =IF(LEN(B10)<50,"—","1) Mirror top JD keywords in Professional Summary 2) Move "&B25&" experience to top 3) Add 1 quantified bullet per top-scoring keyword 4) Re-title header to match JD role 5) Reference JD industry in summary") -> 1) Mirror top JD keywords in Professional Summary 2) Move Technical Program Manager experience to top 3) Add 1 quantified bullet per top-scoring keyword 4) Re-title header to match JD role 5) Reference JD industry in summary
A30: 📊 TRACK-BY-TRACK SCORE BREAKDOWN
A31: Track | B31: Score | Match Level | Progress Bar (20 chars)
A32: 🤖 AI Transformation Manager | B32: =IF(LEN(B10)<50,"—",AI_SCORE!D26&" pts | "&IF(AI_SCORE!D26>=32,"🟢 STRONG",IF(AI_SCORE!D26>=25,"🔵 GOOD",IF(AI_SCORE!D26>=18,"🟡 MODERATE","🔴 WEAK")))&" | "&REPT("█",MIN(20,AI_SCORE!D26/2))&REPT("░",MAX(0,20-MIN(20,AI_SCORE!D26/2)))) -> 17 pts | 🔴 WEAK | ████████░░░░░░░░░░░
A33: ⚙️ Technical Program Manager | B33: =IF(LEN(B10)<50,"—",TPM_SCORE!D26&" pts | "&IF(TPM_SCORE!D26>=32,"🟢 STRONG",IF(TPM_SCORE!D26>=25,"🔵 GOOD",IF(TPM_SCORE!D26>=18,"🟡 MODERATE","🔴 WEAK")))&" | "&REPT("█",MIN(20,TPM_SCORE!D26/2))&REPT("░",MAX(0,20-MIN(20,TPM_SCORE!D26/2)))) -> 22 pts | 🟡 MODERATE | ███████████░░░░░░░░░
A34: 🛠️ IT Delivery Manager | B34: =IF(LEN(B10)<50,"—",ITDM_SCORE!D26&" pts | "&IF(ITDM_SCORE!D26>=32,"🟢 STRONG",IF(ITDM_SCORE!D26>=25,"🔵 GOOD",IF(ITDM_SCORE!D26>=18,"🟡 MODERATE","🔴 WEAK")))&" | "&REPT("█",MIN(20,ITDM_SCORE!D26/2))&REPT("░",MAX(0,20-MIN(20,ITDM_SCORE!D26/2)))) -> 9 pts | 🔴 WEAK | ████░░░░░░░░░░░░░░░
A35: 📦 Product Manager | B35: =IF(LEN(B10)<50,"—",PM_SCORE!D26&" pts | "&IF(PM_SCORE!D26>=32,"🟢 STRONG",IF(PM_SCORE!D26>=25,"🔵 GOOD",IF(PM_SCORE!D26>=18,"🟡 MODERATE","🔴 WEAK")))&" | "&REPT("█",MIN(20,PM_SCORE!D26/2))&REPT("░",MAX(0,20-MIN(20,PM_SCORE!D26/2)))) -> 16 pts | 🔴 WEAK | ████████░░░░░░░░░░░░
A36: 🎯 GAP ANALYSIS — Score Delta vs. Best Fit
A37: AI vs Best | B37: =IF(LEN(B10)<50,"—",(AI_SCORE!D26-MAX(AI_SCORE!D26,TPM_SCORE!D26,ITDM_SCORE!D26))&" pts ("&IF(AI_SCORE!D26=MAX(AI_SCORE!D26,TPM_SCORE!D26,ITDM_SCORE!D26),"🏆 BEST FIT","behind best fit")&")") -> -5 pts (behind best fit)
A38: TPM vs Best | B38: =IF(LEN(B10)<50,"—",(TPM_SCORE!D26-MAX(AI_SCORE!D26,TPM_SCORE!D26,ITDM_SCORE!D26))&" pts ("&IF(TPM_SCORE!D26=MAX(AI_SCORE!D26,TPM_SCORE!D26,ITDM_SCORE!D26),"🏆 BEST FIT","behind best fit")&")") -> 0 pts (🏆 BEST FIT)
A39: ITDM vs Best | B39: =IF(LEN(B10)<50,"—",(ITDM_SCORE!D26-MAX(AI_SCORE!D26,TPM_SCORE!D26,ITDM_SCORE!D26))&" pts ("&IF(ITDM_SCORE!D26=MAX(AI_SCORE!D26,TPM_SCORE!D26,ITDM_SCORE!D26),"🏆 BEST FIT","behind best fit")&")") -> -13 pts (behind best fit)
A40: PM vs Best | B40: =IF(LEN(B10)<50,"—",(PM_SCORE!D26-MAX(AI_SCORE!D26,TPM_SCORE!D26,ITDM_SCORE!D26,PM_SCORE!D26))&" pts ("&IF(PM_SCORE!D26=MAX(AI_SCORE!D26,TPM_SCORE!D26,ITDM_SCORE!D26,PM_SCORE!D26),"🏆 BEST FIT","behind best fit")&")") -> -6 pts (behind best fit)
A41: ℹ️ How it works | B41: Paste JD into B10 → All 3 track scores update instantly → Best-fit resume appears at row 25 → Radar chart on FINAL_RECOMMENDATION visualizes 3-track comparison. No manual entry required.
A43: TOP MISSING KEYWORDS - Best Fit
A44: For Best-Fit Track | B44: =IF(LEN(B10)<50,"Paste JD first","Top 5 for: "&B25) -> Top 5 for: Technical Program Manager
A45: ① Missing #1 | B45: =IF(LEN(B10)<50,"—",IF(B25="AI Transformation Manager",AI_SCORE!B32,IF(B25="Technical Program Manager",TPM_SCORE!B32,IF(B25="IT Delivery Manager",ITDM_SCORE!B32,PM_SCORE!B32)))) -> Technical program management
A46: ② Missing #2 | B46: =IF(LEN(B10)<50,"—",IF(B25="AI Transformation Manager",AI_SCORE!B33,IF(B25="Technical Program Manager",TPM_SCORE!B33,IF(B25="IT Delivery Manager",ITDM_SCORE!B33,PM_SCORE!B33)))) -> Program delivery
A47: ③ Missing #3 | B47: =IF(LEN(B10)<50,"—",IF(B25="AI Transformation Manager",AI_SCORE!B34,IF(B25="Technical Program Manager",TPM_SCORE!B34,IF(B25="IT Delivery Manager",ITDM_SCORE!B34,PM_SCORE!B34)))) -> Risk management
A48: ④ Missing #4 | B48: =IF(LEN(B10)<50,"—",IF(B25="AI Transformation Manager",AI_SCORE!B35,IF(B25="Technical Program Manager",TPM_SCORE!B35,IF(B25="IT Delivery Manager",ITDM_SCORE!B35,PM_SCORE!B35)))) -> Change management
A49: ⑤ Missing #5 | B49: =IF(LEN(B10)<50,"—",IF(B25="AI Transformation Manager",AI_SCORE!B36,IF(B25="Technical Program Manager",TPM_SCORE!B36,IF(B25="IT Delivery Manager",ITDM_SCORE!B36,PM_SCORE!B36)))) -> Release management
A50: 💡 Score Boost | B50: =IF(LEN(B10)<50,"—","+20 pts potential (boosts "&B25&" to "&(MAX(AI_SCORE!D26,TPM_SCORE!D26,ITDM_SCORE!D26,PM_SCORE!D26)+20)&" pts)") -> +20 pts potential (boosts Technical Program Manager to 42 pts)
A52: ✍️ Resume Bullets | B52: =IF(LEN(B10)<50,"⏳ Paste JD to see bullet suggestions","See BULLET_GENERATOR sheet → "&COUNTIF(BULLET_GENERATOR!E4:E63,"🟢 USE THIS")&" bullets recommended for your JD") -> See BULLET_GENERATOR sheet → 20 bullets recommended for your JD
A54: ⚠️ JD QUALITY & ATS WARNINGS — Data-quality checks before you trust the score
A55: 📏 JD Word Count | B55: =IF(LEN(B10)<50,"⏳ Waiting for JD input",IF(LEN(B10)-LEN(SUBSTITUTE(B10," ",""))+1<150,"🔴 TOO SHORT ("&(LEN(B10)-LEN(SUBSTITUTE(B10," ",""))+1)&" words) — Score may be unreliable. Add more JD content.",IF(LEN(B10)-LEN(SUBSTITUTE(B10," ",""))+1<300,"🟡 SHORT ("&(LEN(B10)-LEN(SUBSTITUTE(B10," ",""))+1)&" words) — Adequate but keyword coverage may be limited",IF(LEN(B10)-LEN(SUBSTITUTE(B10," ",""))+1<800,"🟢 GOOD ("&(LEN(B10)-LEN(SUBSTITUTE(B10," ",""))+1)&" words) — Ideal length for reliable scoring","🔵 LONG ("&(LEN(B10)-LEN(SUBSTITUTE(B10," ",""))+1)&" words) — Comprehensive JD, scores are highly reliable")))) -> 🔵 LONG (892 words) — Comprehensive JD, scores are highly reliable
A56: 📝 JD Character Count | B56: =IF(LEN(B10)<50,"⏳ Waiting",LEN(B10)&" characters ("&IF(LEN(B10)<500,"🔴 too brief",IF(LEN(B10)<1500,"🟡 acceptable",IF(LEN(B10)<5000,"🟢 comprehensive","🔵 very detailed")))&")") -> 6943 characters (🔵 very detailed)
A57: 🚩 Technical Red Flags | B57: =IF(LEN(B10)<50,"⏳ Waiting",IF((IF(ISNUMBER(SEARCH("python",B12)),1,0)+IF(ISNUMBER(SEARCH("tensorflow",B12)),1,0)+IF(ISNUMBER(SEARCH("pytorch",B12)),1,0)+IF(ISNUMBER(SEARCH("data scientist",B12)),1,0)+IF(ISNUMBER(SEARCH("ml engineer",B12)),1,0)+IF(ISNUMBER(SEARCH("hands-on coding",B12)),1,0)+IF(ISNUMBER(SEARCH("software engineer",B12)),1,0)+IF(ISNUMBER(SEARCH("java developer",B12)),1,0))>=3,"🔴 HIGH ("&(IF(ISNUMBER(SEARCH("python",B12)),1,0)+IF(ISNUMBER(SEARCH("tensorflow",B12)),1,0)+IF(ISNUMBER(SEARCH("pytorch",B12)),1,0)+IF(ISNUMBER(SEARCH("data scientist",B12)),1,0)+IF(ISNUMBER(SEARCH("ml engineer",B12)),1,0)+IF(ISNUMBER(SEARCH("hands-on coding",B12)),1,0)+IF(ISNUMBER(SEARCH("software engineer",B12)),1,0)+IF(ISNUMBER(SEARCH("java developer",B12)),1,0))&" flags) — JD may require hands-on technical work. Management resume may not fit.",IF((IF(ISNUMBER(SEARCH("python",B12)),1,0)+IF(ISNUMBER(SEARCH("tensorflow",B12)),1,0)+IF(ISNUMBER(SEARCH("pytorch",B12)),1,0)+IF(ISNUMBER(SEARCH("data scientist",B12)),1,0)+IF(ISNUMBER(SEARCH("ml engineer",B12)),1,0)+IF(ISNUMBER(SEARCH("hands-on coding",B12)),1,0)+IF(ISNUMBER(SEARCH("software engineer",B12)),1,0)+IF(ISNUMBER(SEARCH("java developer",B12)),1,0))>=1,"🟡 SOME ("&(IF(ISNUMBER(SEARCH("python",B12)),1,0)+IF(ISNUMBER(SEARCH("tensorflow",B12)),1,0)+IF(ISNUMBER(SEARCH("pytorch",B12)),1,0)+IF(ISNUMBER(SEARCH("data scientist",B12)),1,0)+IF(ISNUMBER(SEARCH("ml engineer",B12)),1,0)+IF(ISNUMBER(SEARCH("hands-on coding",B12)),1,0)+IF(ISNUMBER(SEARCH("software engineer",B12)),1,0)+IF(ISNUMBER(SEARCH("java developer",B12)),1,0))&" flags) — Minor hands-on aspects, but management framing likely still works","🟢 CLEAN — No hands-on technical red flags detected. Good fit for management resume."))) -> 🟢 CLEAN — No hands-on technical red flags detected. Good fit for management resume.
A58: 👔 Management Signals | B58: =IF(LEN(B10)<50,"⏳ Waiting",(IF(ISNUMBER(SEARCH("manager",B12)),1,0)+IF(ISNUMBER(SEARCH("director",B12)),1,0)+IF(ISNUMBER(SEARCH("head of",B12)),1,0)+IF(ISNUMBER(SEARCH("lead ",B12)),1,0)+IF(ISNUMBER(SEARCH("leadership",B12)),1,0)+IF(ISNUMBER(SEARCH("stakeholder",B12)),1,0)+IF(ISNUMBER(SEARCH("strategy",B12)),1,0)+IF(ISNUMBER(SEARCH("govern",B12)),1,0)+IF(ISNUMBER(SEARCH("roadmap",B12)),1,0))&" signals detected "&IF((IF(ISNUMBER(SEARCH("manager",B12)),1,0)+IF(ISNUMBER(SEARCH("director",B12)),1,0)+IF(ISNUMBER(SEARCH("head of",B12)),1,0)+IF(ISNUMBER(SEARCH("lead ",B12)),1,0)+IF(ISNUMBER(SEARCH("leadership",B12)),1,0)+IF(ISNUMBER(SEARCH("stakeholder",B12)),1,0)+IF(ISNUMBER(SEARCH("strategy",B12)),1,0)+IF(ISNUMBER(SEARCH("govern",B12)),1,0)+IF(ISNUMBER(SEARCH("roadmap",B12)),1,0))>=5,"→ 🟢 STRONG management role",IF((IF(ISNUMBER(SEARCH("manager",B12)),1,0)+IF(ISNUMBER(SEARCH("director",B12)),1,0)+IF(ISNUMBER(SEARCH("head of",B12)),1,0)+IF(ISNUMBER(SEARCH("lead ",B12)),1,0)+IF(ISNUMBER(SEARCH("leadership",B12)),1,0)+IF(ISNUMBER(SEARCH("stakeholder",B12)),1,0)+IF(ISNUMBER(SEARCH("strategy",B12)),1,0)+IF(ISNUMBER(SEARCH("govern",B12)),1,0)+IF(ISNUMBER(SEARCH("roadmap",B12)),1,0))>=3,"→ 🟡 MODERATE management role","→ 🔴 WEAK management signals — may be an IC role"))) -> 6 signals detected → 🟢 STRONG management role
A59: 📋 JD Metadata Complete | B59: =IF(LEN(B10)<50,"⏳ Waiting",(IF(B3="",0,1)+IF(B4="",0,1)+IF(B5="",0,1)+IF(B6="",0,1)+IF(B7="",0,1))&" of 5 filled "&IF((IF(B3="",0,1)+IF(B4="",0,1)+IF(B5="",0,1)+IF(B6="",0,1)+IF(B7="",0,1))=5,"→ 🟢 COMPLETE",IF((IF(B3="",0,1)+IF(B4="",0,1)+IF(B5="",0,1)+IF(B6="",0,1)+IF(B7="",0,1))>=3,"→ 🟡 PARTIAL — fill Company/Role/Location for full context","→ 🔴 INCOMPLETE — fill in Company, Role, Location (rows 3-7) above"))) -> 0 of 5 filled → 🔴 INCOMPLETE — fill in Company, Role, Location (rows 3-7) above
A60: 📑 JD Structure Quality | B60: =IF(LEN(B10)<50,"⏳ Waiting",(IF(OR(ISNUMBER(SEARCH("responsibilit",B12)),ISNUMBER(SEARCH("what you'll do",B12)),ISNUMBER(SEARCH("what you will do",B12))),1,0)+IF(OR(ISNUMBER(SEARCH("requirement",B12)),ISNUMBER(SEARCH("qualification",B12)),ISNUMBER(SEARCH("must have",B12)),ISNUMBER(SEARCH("we're looking for",B12))),1,0)+IF(OR(ISNUMBER(SEARCH("preferred",B12)),ISNUMBER(SEARCH("nice to have",B12)),ISNUMBER(SEARCH("bonus",B12))),1,0)+IF(OR(ISNUMBER(SEARCH("about the company",B12)),ISNUMBER(SEARCH("about us",B12)),ISNUMBER(SEARCH("who we are",B12))),1,0))&" of 4 sections detected "&IF((IF(OR(ISNUMBER(SEARCH("responsibilit",B12)),ISNUMBER(SEARCH("what you'll do",B12)),ISNUMBER(SEARCH("what you will do",B12))),1,0)+IF(OR(ISNUMBER(SEARCH("requirement",B12)),ISNUMBER(SEARCH("qualification",B12)),ISNUMBER(SEARCH("must have",B12)),ISNUMBER(SEARCH("we're looking for",B12))),1,0)+IF(OR(ISNUMBER(SEARCH("preferred",B12)),ISNUMBER(SEARCH("nice to have",B12)),ISNUMBER(SEARCH("bonus",B12))),1,0)+IF(OR(ISNUMBER(SEARCH("about the company",B12)),ISNUMBER(SEARCH("about us",B12)),ISNUMBER(SEARCH("who we are",B12))),1,0))>=3,"→ 🟢 Well-structured",IF((IF(OR(ISNUMBER(SEARCH("responsibilit",B12)),ISNUMBER(SEARCH("what you'll do",B12)),ISNUMBER(SEARCH("what you will do",B12))),1,0)+IF(OR(ISNUMBER(SEARCH("requirement",B12)),ISNUMBER(SEARCH("qualification",B12)),ISNUMBER(SEARCH("must have",B12)),ISNUMBER(SEARCH("we're looking for",B12))),1,0)+IF(OR(ISNUMBER(SEARCH("preferred",B12)),ISNUMBER(SEARCH("nice to have",B12)),ISNUMBER(SEARCH("bonus",B12))),1,0)+IF(OR(ISNUMBER(SEARCH("about the company",B12)),ISNUMBER(SEARCH("about us",B12)),ISNUMBER(SEARCH("who we are",B12))),1,0))>=2,"→ 🟡 Partial structure","→ 🔴 Weak structure — JD may be a snippet or summary"))) -> 3 of 4 sections detected → 🟢 Well-structured
A61: 💰 Salary Transparency | B61: =IF(LEN(B10)<50,"⏳ Waiting",IF(ISNUMBER(SEARCH("$",B10)),"🟢 SALARY DISCLOSED — $ figure present in JD",IF(OR(ISNUMBER(SEARCH("compensation",B12)),ISNUMBER(SEARCH("pay range",B12)),ISNUMBER(SEARCH("base pay",B12)),ISNUMBER(SEARCH("total comp",B12))),"🟡 COMP MENTIONED — no explicit $ figure","🔴 NOT DISCLOSED — negotiate carefully or ask upfront"))) -> 🔴 NOT DISCLOSED — negotiate carefully or ask upfront
A62: 🎯 DATA QUALITY CONFIDENCE | B62: =IF(LEN(B10)<50,"⏳ Waiting for JD input",(IF(LEN(B10)-LEN(SUBSTITUTE(B10," ",""))+1>=300,30,IF(LEN(B10)-LEN(SUBSTITUTE(B10," ",""))+1>=150,20,10))+IF((IF(ISNUMBER(SEARCH("python",B12)),1,0)+IF(ISNUMBER(SEARCH("tensorflow",B12)),1,0)+IF(ISNUMBER(SEARCH("pytorch",B12)),1,0)+IF(ISNUMBER(SEARCH("data scientist",B12)),1,0)+IF(ISNUMBER(SEARCH("ml engineer",B12)),1,0)+IF(ISNUMBER(SEARCH("hands-on coding",B12)),1,0))<=1,20,IF((IF(ISNUMBER(SEARCH("python",B12)),1,0)+IF(ISNUMBER(SEARCH("tensorflow",B12)),1,0)+IF(ISNUMBER(SEARCH("pytorch",B12)),1,0)+IF(ISNUMBER(SEARCH("data scientist",B12)),1,0)+IF(ISNUMBER(SEARCH("ml engineer",B12)),1,0)+IF(ISNUMBER(SEARCH("hands-on coding",B12)),1,0))<=3,10,0))+IF((IF(ISNUMBER(SEARCH("manager",B12)),1,0)+IF(ISNUMBER(SEARCH("director",B12)),1,0)+IF(ISNUMBER(SEARCH("head of",B12)),1,0)+IF(ISNUMBER(SEARCH("leadership",B12)),1,0)+IF(ISNUMBER(SEARCH("stakeholder",B12)),1,0))>=3,25,IF((IF(ISNUMBER(SEARCH("manager",B12)),1,0)+IF(ISNUMBER(SEARCH("director",B12)),1,0)+IF(ISNUMBER(SEARCH("head of",B12)),1,0)+IF(ISNUMBER(SEARCH("leadership",B12)),1,0)+IF(ISNUMBER(SEARCH("stakeholder",B12)),1,0))>=1,15,5))+IF((IF(OR(ISNUMBER(SEARCH("responsibilit",B12)),ISNUMBER(SEARCH("what you'll do",B12))),1,0)+IF(OR(ISNUMBER(SEARCH("requirement",B12)),ISNUMBER(SEARCH("qualification",B12))),1,0))>=2,15,IF((IF(OR(ISNUMBER(SEARCH("responsibilit",B12)),ISNUMBER(SEARCH("what you'll do",B12))),1,0)+IF(OR(ISNUMBER(SEARCH("requirement",B12)),ISNUMBER(SEARCH("qualification",B12))),1,0))>=1,10,5))+IF((IF(B3="",0,1)+IF(B4="",0,1)+IF(B5="",0,1))>=2,10,IF((IF(B3="",0,1)+IF(B4="",0,1)+IF(B5="",0,1))>=1,5,0)))&"/100 confidence — "&IF((IF(LEN(B10)-LEN(SUBSTITUTE(B10," ",""))+1>=300,30,IF(LEN(B10)-LEN(SUBSTITUTE(B10," ",""))+1>=150,20,10))+IF((IF(ISNUMBER(SEARCH("python",B12)),1,0)+IF(ISNUMBER(SEARCH("tensorflow",B12)),1,0)+IF(ISNUMBER(SEARCH("pytorch",B12)),1,0)+IF(ISNUMBER(SEARCH("data scientist",B12)),1,0)+IF(ISNUMBER(SEARCH("ml engineer",B12)),1,0)+IF(ISNUMBER(SEARCH("hands-on coding",B12)),1,0))<=1,20,IF((IF(ISNUMBER(SEARCH("python",B12)),1,0)+IF(ISNUMBER(SEARCH("tensorflow",B12)),1,0)+IF(ISNUMBER(SEARCH("pytorch",B12)),1,0)+IF(ISNUMBER(SEARCH("data scientist",B12)),1,0)+IF(ISNUMBER(SEARCH("ml engineer",B12)),1,0)+IF(ISNUMBER(SEARCH("hands-on coding",B12)),1,0))<=3,10,0))+IF((IF(ISNUMBER(SEARCH("manager",B12)),1,0)+IF(ISNUMBER(SEARCH("director",B12)),1,0)+IF(ISNUMBER(SEARCH("head of",B12)),1,0)+IF(ISNUMBER(SEARCH("leadership",B12)),1,0)+IF(ISNUMBER(SEARCH("stakeholder",B12)),1,0))>=3,25,IF((IF(ISNUMBER(SEARCH("manager",B12)),1,0)+IF(ISNUMBER(SEARCH("director",B12)),1,0)+IF(ISNUMBER(SEARCH("head of",B12)),1,0)+IF(ISNUMBER(SEARCH("leadership",B12)),1,0)+IF(ISNUMBER(SEARCH("stakeholder",B12)),1,0))>=1,15,5))+IF((IF(OR(ISNUMBER(SEARCH("responsibilit",B12)),ISNUMBER(SEARCH("what you'll do",B12))),1,0)+IF(OR(ISNUMBER(SEARCH("requirement",B12)),ISNUMBER(SEARCH("qualification",B12))),1,0))>=2,15,IF((IF(OR(ISNUMBER(SEARCH("responsibilit",B12)),ISNUMBER(SEARCH("what you'll do",B12))),1,0)+IF(OR(ISNUMBER(SEARCH("requirement",B12)),ISNUMBER(SEARCH("qualification",B12))),1,0))>=1,10,5))+IF((IF(B3="",0,1)+IF(B4="",0,1)+IF(B5="",0,1))>=2,10,IF((IF(B3="",0,1)+IF(B4="",0,1)+IF(B5="",0,1))>=1,5,0)))>=80,"🟢 HIGH — trust the scores",IF((IF(LEN(B10)-LEN(SUBSTITUTE(B10," ",""))+1>=300,30,IF(LEN(B10)-LEN(SUBSTITUTE(B10," ",""))+1>=150,20,10))+IF((IF(ISNUMBER(SEARCH("python",B12)),1,0)+IF(ISNUMBER(SEARCH("tensorflow",B12)),1,0)+IF(ISNUMBER(SEARCH("pytorch",B12)),1,0)+IF(ISNUMBER(SEARCH("data scientist",B12)),1,0)+IF(ISNUMBER(SEARCH("ml engineer",B12)),1,0)+IF(ISNUMBER(SEARCH("hands-on coding",B12)),1,0))<=1,20,IF((IF(ISNUMBER(SEARCH("python",B12)),1,0)+IF(ISNUMBER(SEARCH("tensorflow",B12)),1,0)+IF(ISNUMBER(SEARCH("pytorch",B12)),1,0)+IF(ISNUMBER(SEARCH("data scientist",B12)),1,0)+IF(ISNUMBER(SEARCH("ml engineer",B12)),1,0)+IF(ISNUMBER(SEARCH("hands-on coding",B12)),1,0))<=3,10,0))+IF((IF(ISNUMBER(SEARCH("manager",B12)),1,0)+IF(ISNUMBER(SEARCH("director",B12)),1,0)+IF(ISNUMBER(SEARCH("head of",B12)),1,0)+IF(ISNUMBER(SEARCH("leadership",B12)),1,0)+IF(ISNUMBER(SEARCH("stakeholder",B12)),1,0))>=3,25,IF((IF(ISNUMBER(SEARCH("manager",B12)),1,0)+IF(ISNUMBER(SEARCH("director",B12)),1,0)+IF(ISNUMBER(SEARCH("head of",B12)),1,0)+IF(ISNUMBER(SEARCH("leadership",B12)),1,0)+IF(ISNUMBER(SEARCH("stakeholder",B12)),1,0))>=1,15,5))+IF((IF(OR(ISNUMBER(SEARCH("responsibilit",B12)),ISNUMBER(SEARCH("what you'll do",B12))),1,0)+IF(OR(ISNUMBER(SEARCH("requirement",B12)),ISNUMBER(SEARCH("qualification",B12))),1,0))>=2,15,IF((IF(OR(ISNUMBER(SEARCH("responsibilit",B12)),ISNUMBER(SEARCH("what you'll do",B12))),1,0)+IF(OR(ISNUMBER(SEARCH("requirement",B12)),ISNUMBER(SEARCH("qualification",B12))),1,0))>=1,10,5))+IF((IF(B3="",0,1)+IF(B4="",0,1)+IF(B5="",0,1))>=2,10,IF((IF(B3="",0,1)+IF(B4="",0,1)+IF(B5="",0,1))>=1,5,0)))>=60,"🔵 GOOD — scores are reliable",IF((IF(LEN(B10)-LEN(SUBSTITUTE(B10," ",""))+1>=300,30,IF(LEN(B10)-LEN(SUBSTITUTE(B10," ",""))+1>=150,20,10))+IF((IF(ISNUMBER(SEARCH("python",B12)),1,0)+IF(ISNUMBER(SEARCH("tensorflow",B12)),1,0)+IF(ISNUMBER(SEARCH("pytorch",B12)),1,0)+IF(ISNUMBER(SEARCH("data scientist",B12)),1,0)+IF(ISNUMBER(SEARCH("ml engineer",B12)),1,0)+IF(ISNUMBER(SEARCH("hands-on coding",B12)),1,0))<=1,20,IF((IF(ISNUMBER(SEARCH("python",B12)),1,0)+IF(ISNUMBER(SEARCH("tensorflow",B12)),1,0)+IF(ISNUMBER(SEARCH("pytorch",B12)),1,0)+IF(ISNUMBER(SEARCH("data scientist",B12)),1,0)+IF(ISNUMBER(SEARCH("ml engineer",B12)),1,0)+IF(ISNUMBER(SEARCH("hands-on coding",B12)),1,0))<=3,10,0))+IF((IF(ISNUMBER(SEARCH("manager",B12)),1,0)+IF(ISNUMBER(SEARCH("director",B12)),1,0)+IF(ISNUMBER(SEARCH("head of",B12)),1,0)+IF(ISNUMBER(SEARCH("leadership",B12)),1,0)+IF(ISNUMBER(SEARCH("stakeholder",B12)),1,0))>=3,25,IF((IF(ISNUMBER(SEARCH("manager",B12)),1,0)+IF(ISNUMBER(SEARCH("director",B12)),1,0)+IF(ISNUMBER(SEARCH("head of",B12)),1,0)+IF(ISNUMBER(SEARCH("leadership",B12)),1,0)+IF(ISNUMBER(SEARCH("stakeholder",B12)),1,0))>=1,15,5))+IF((IF(OR(ISNUMBER(SEARCH("responsibilit",B12)),ISNUMBER(SEARCH("what you'll do",B12))),1,0)+IF(OR(ISNUMBER(SEARCH("requirement",B12)),ISNUMBER(SEARCH("qualification",B12))),1,0))>=2,15,IF((IF(OR(ISNUMBER(SEARCH("responsibilit",B12)),ISNUMBER(SEARCH("what you'll do",B12))),1,0)+IF(OR(ISNUMBER(SEARCH("requirement",B12)),ISNUMBER(SEARCH("qualification",B12))),1,0))>=1,10,5))+IF((IF(B3="",0,1)+IF(B4="",0,1)+IF(B5="",0,1))>=2,10,IF((IF(B3="",0,1)+IF(B4="",0,1)+IF(B5="",0,1))>=1,5,0)))>=40,"🟡 MODERATE — interpret scores with care","🔴 LOW — add more JD content or metadata")))) -> 80/100 confidence — 🟢 HIGH — trust the scores
A63: 🚦 SHOULD YOU APPLY? | B63: =IF(LEN(B10)<50,"⏳ Waiting",IF(AND(MAX(AI_SCORE!D26,TPM_SCORE!D26,ITDM_SCORE!D26,PM_SCORE!D26)>=25,(IF(ISNUMBER(SEARCH("python",B12)),1,0)+IF(ISNUMBER(SEARCH("tensorflow",B12)),1,0)+IF(ISNUMBER(SEARCH("pytorch",B12)),1,0)+IF(ISNUMBER(SEARCH("data scientist",B12)),1,0)+IF(ISNUMBER(SEARCH("ml engineer",B12)),1,0))<3),"🟢 YES — Strong match + management-friendly. Apply with confidence.",IF(AND(MAX(AI_SCORE!D26,TPM_SCORE!D26,ITDM_SCORE!D26,PM_SCORE!D26)>=18,(IF(ISNUMBER(SEARCH("python",B12)),1,0)+IF(ISNUMBER(SEARCH("tensorflow",B12)),1,0)+IF(ISNUMBER(SEARCH("pytorch",B12)),1,0)+IF(ISNUMBER(SEARCH("data scientist",B12)),1,0)+IF(ISNUMBER(SEARCH("ml engineer",B12)),1,0))<3),"🟡 MAYBE — Moderate match. Tailor heavily before applying.",IF((IF(ISNUMBER(SEARCH("python",B12)),1,0)+IF(ISNUMBER(SEARCH("tensorflow",B12)),1,0)+IF(ISNUMBER(SEARCH("pytorch",B12)),1,0)+IF(ISNUMBER(SEARCH("data scientist",B12)),1,0)+IF(ISNUMBER(SEARCH("ml engineer",B12)),1,0))>=3,"🔴 SKIP — JD requires hands-on technical work. Not a fit for management resume.","🔴 SKIP — Low score. Not a strong fit for any of the 4 tracks.")))) -> 🟡 MAYBE — Moderate match. Tailor heavily before applying.
A65: ◆ ◆ ◆ END OF DASHBOARD ◆ ◆ ◆

Sheet AI_SCORE
A1: AI Transformation Manager - Scoring
A3: Keyword / Theme | B3: Weight | C3: Auto Score (0,1,2) | D3: Weighted Score | E3: Notes | H3: Contribution
A4: AI transformation | B4: 2 | C4: =IF(LEN(JD_INPUT!$B$12)<5,0,MIN(2,SUMPRODUCT(--ISNUMBER(SEARCH(TRIM(MID(SUBSTITUTE(KEYWORDS!$B$3,"|",REPT(" ",200)),(ROW(INDIRECT("1:"&KEYWORDS!$C$3))-1)*200+1,200)),JD_INPUT!$B$12))))) -> 0 | D4: =B4*C4 -> 0 | E4: =IF(C4=0,"No keyword match",IF(C4=1,"1 variant matched","2+ variants matched")) -> No keyword match | G4: =IF(C4=0,COUNTIF($C$4:C4,0),"") -> 1 | H4: =IF(D4=0,REPT("░",20),REPT("█",MIN(20,D4*5))&REPT("░",MAX(0,20-MIN(20,D4*5)))) -> ░░░░░░░░░░░░░░░░░░░░
A5: Digital transformation | B5: 2 | C5: =IF(LEN(JD_INPUT!$B$12)<5,0,MIN(2,SUMPRODUCT(--ISNUMBER(SEARCH(TRIM(MID(SUBSTITUTE(KEYWORDS!$B$4,"|",REPT(" ",200)),(ROW(INDIRECT("1:"&KEYWORDS!$C$4))-1)*200+1,200)),JD_INPUT!$B$12))))) -> 0 | D5: =B5*C5 -> 0 | E5: =IF(C5=0,"No keyword match",IF(C5=1,"1 variant matched","2+ variants matched")) -> No keyword match | G5: =IF(C5=0,COUNTIF($C$4:C5,0),"") -> 2 | H5: =IF(D5=0,REPT("░",20),REPT("█",MIN(20,D5*5))&REPT("░",MAX(0,20-MIN(20,D5*5)))) -> ░░░░░░░░░░░░░░░░░░░░
A6: Generative AI / GenAI | B6: 2 | C6: =IF(LEN(JD_INPUT!$B$12)<5,0,MIN(2,SUMPRODUCT(--ISNUMBER(SEARCH(TRIM(MID(SUBSTITUTE(KEYWORDS!$B$5,"|",REPT(" ",200)),(ROW(INDIRECT("1:"&KEYWORDS!$C$5))-1)*200+1,200)),JD_INPUT!$B$12))))) -> 0 | D6: =B6*C6 -> 0 | E6: =IF(C6=0,"No keyword match",IF(C6=1,"1 variant matched","2+ variants matched")) -> No keyword match | G6: =IF(C6=0,COUNTIF($C$4:C6,0),"") -> 3 | H6: =IF(D6=0,REPT("░",20),REPT("█",MIN(20,D6*5))&REPT("░",MAX(0,20-MIN(20,D6*5)))) -> ░░░░░░░░░░░░░░░░░░░░
A7: Intelligent automation | B7: 2 | C7: =IF(LEN(JD_INPUT!$B$12)<5,0,MIN(2,SUMPRODUCT(--ISNUMBER(SEARCH(TRIM(MID(SUBSTITUTE(KEYWORDS!$B$6,"|",REPT(" ",200)),(ROW(INDIRECT("1:"&KEYWORDS!$C$6))-1)*200+1,200)),JD_INPUT!$B$12))))) -> 0 | D7: =B7*C7 -> 0 | E7: =IF(C7=0,"No keyword match",IF(C7=1,"1 variant matched","2+ variants matched")) -> No keyword match | G7: =IF(C7=0,COUNTIF($C$4:C7,0),"") -> 4 | H7: =IF(D7=0,REPT("░",20),REPT("█",MIN(20,D7*5))&REPT("░",MAX(0,20-MIN(20,D7*5)))) -> ░░░░░░░░░░░░░░░░░░░░
A8: AI adoption / AI strategy | B8: 2 | C8: =IF(LEN(JD_INPUT!$B$12)<5,0,MIN(2,SUMPRODUCT(--ISNUMBER(SEARCH(TRIM(MID(SUBSTITUTE(KEYWORDS!$B$7,"|",REPT(" ",200)),(ROW(INDIRECT("1:"&KEYWORDS!$C$7))-1)*200+1,200)),JD_INPUT!$B$12))))) -> 0 | D8: =B8*C8 -> 0 | E8: =IF(C8=0,"No keyword match",IF(C8=1,"1 variant matched","2+ variants matched")) -> No keyword match | G8: =IF(C8=0,COUNTIF($C$4:C8,0),"") -> 5 | H8: =IF(D8=0,REPT("░",20),REPT("█",MIN(20,D8*5))&REPT("░",MAX(0,20-MIN(20,D8*5)))) -> ░░░░░░░░░░░░░░░░░░░░
A9: Transformation roadmap | B9: 2 | C9: =IF(LEN(JD_INPUT!$B$12)<5,0,MIN(2,SUMPRODUCT(--ISNUMBER(SEARCH(TRIM(MID(SUBSTITUTE(KEYWORDS!$B$8,"|",REPT(" ",200)),(ROW(INDIRECT("1:"&KEYWORDS!$C$8))-1)*200+1,200)),JD_INPUT!$B$12))))) -> 0 | D9: =B9*C9 -> 0 | E9: =IF(C9=0,"No keyword match",IF(C9=1,"1 variant matched","2+ variants matched")) -> No keyword match | G9: =IF(C9=0,COUNTIF($C$4:C9,0),"") -> 6 | H9: =IF(D9=0,REPT("░",20),REPT("█",MIN(20,D9*5))&REPT("░",MAX(0,20-MIN(20,D9*5)))) -> ░░░░░░░░░░░░░░░░░░░░
A10: Enterprise modernization | B10: 2 | C10: =IF(LEN(JD_INPUT!$B$12)<5,0,MIN(2,SUMPRODUCT(--ISNUMBER(SEARCH(TRIM(MID(SUBSTITUTE(KEYWORDS!$B$9,"|",REPT(" ",200)),(ROW(INDIRECT("1:"&KEYWORDS!$C$9))-1)*200+1,200)),JD_INPUT!$B$12))))) -> 0 | D10: =B10*C10 -> 0 | E10: =IF(C10=0,"No keyword match",IF(C10=1,"1 variant matched","2+ variants matched")) -> No keyword match | G10: =IF(C10=0,COUNTIF($C$4:C10,0),"") -> 7 | H10: =IF(D10=0,REPT("░",20),REPT("█",MIN(20,D10*5))&REPT("░",MAX(0,20-MIN(20,D10*5)))) -> ░░░░░░░░░░░░░░░░░░░░
A11: Change management | B11: 2 | C11: =IF(LEN(JD_INPUT!$B$12)<5,0,MIN(2,SUMPRODUCT(--ISNUMBER(SEARCH(TRIM(MID(SUBSTITUTE(KEYWORDS!$B$10,"|",REPT(" ",200)),(ROW(INDIRECT("1:"&KEYWORDS!$C$10))-1)*200+1,200)),JD_INPUT!$B$12))))) -> 1 | D11: =B11*C11 -> 2 | E11: =IF(C11=0,"No keyword match",IF(C11=1,"1 variant matched","2+ variants matched")) -> 1 variant matched | G11: =IF(C11=0,COUNTIF($C$4:C11,0),"") | H11: =IF(D11=0,REPT("░",20),REPT("█",MIN(20,D11*5))&REPT("░",MAX(0,20-MIN(20,D11*5)))) -> ██████████░░░░░░░░░░
A12: Stakeholder governance | B12: 2 | C12: =IF(LEN(JD_INPUT!$B$12)<5,0,MIN(2,SUMPRODUCT(--ISNUMBER(SEARCH(TRIM(MID(SUBSTITUTE(KEYWORDS!$B$11,"|",REPT(" ",200)),(ROW(INDIRECT("1:"&KEYWORDS!$C$11))-1)*200+1,200)),JD_INPUT!$B$12))))) -> 2 | D12: =B12*C12 -> 4 | E12: =IF(C12=0,"No keyword match",IF(C12=1,"1 variant matched","2+ variants matched")) -> 2+ variants matched | G12: =IF(C12=0,COUNTIF($C$4:C12,0),"") | H12: =IF(D12=0,REPT("░",20),REPT("█",MIN(20,D12*5))&REPT("░",MAX(0,20-MIN(20,D12*5)))) -> ████████████████████
A13: CRM transformation | B13: 2 | C13: =IF(LEN(JD_INPUT!$B$12)<5,0,MIN(2,SUMPRODUCT(--ISNUMBER(SEARCH(TRIM(MID(SUBSTITUTE(KEYWORDS!$B$12,"|",REPT(" ",200)),(ROW(INDIRECT("1:"&KEYWORDS!$C$12))-1)*200+1,200)),JD_INPUT!$B$12))))) -> 0 | D13: =B13*C13 -> 0 | E13: =IF(C13=0,"No keyword match",IF(C13=1,"1 variant matched","2+ variants matched")) -> No keyword match | G13: =IF(C13=0,COUNTIF($C$4:C13,0),"") -> 8 | H13: =IF(D13=0,REPT("░",20),REPT("█",MIN(20,D13*5))&REPT("░",MAX(0,20-MIN(20,D13*5)))) -> ░░░░░░░░░░░░░░░░░░░░
A14: Salesforce / Siebel / ServiceNow | B14: 2 | C14: =IF(LEN(JD_INPUT!$B$12)<5,0,MIN(2,SUMPRODUCT(--ISNUMBER(SEARCH(TRIM(MID(SUBSTITUTE(KEYWORDS!$B$13,"|",REPT(" ",200)),(ROW(INDIRECT("1:"&KEYWORDS!$C$13))-1)*200+1,200)),JD_INPUT!$B$12))))) -> 0 | D14: =B14*C14 -> 0 | E14: =IF(C14=0,"No keyword match",IF(C14=1,"1 variant matched","2+ variants matched")) -> No keyword match | G14: =IF(C14=0,COUNTIF($C$4:C14,0),"") -> 9 | H14: =IF(D14=0,REPT("░",20),REPT("█",MIN(20,D14*5))&REPT("░",MAX(0,20-MIN(20,D14*5)))) -> ░░░░░░░░░░░░░░░░░░░░
A15: Cloud migration | B15: 2 | C15: =IF(LEN(JD_INPUT!$B$12)<5,0,MIN(2,SUMPRODUCT(--ISNUMBER(SEARCH(TRIM(MID(SUBSTITUTE(KEYWORDS!$B$14,"|",REPT(" ",200)),(ROW(INDIRECT("1:"&KEYWORDS!$C$14))-1)*200+1,200)),JD_INPUT!$B$12))))) -> 0 | D15: =B15*C15 -> 0 | E15: =IF(C15=0,"No keyword match",IF(C15=1,"1 variant matched","2+ variants matched")) -> No keyword match | G15: =IF(C15=0,COUNTIF($C$4:C15,0),"") -> 10 | H15: =IF(D15=0,REPT("░",20),REPT("█",MIN(20,D15*5))&REPT("░",MAX(0,20-MIN(20,D15*5)))) -> ░░░░░░░░░░░░░░░░░░░░
A16: Process optimization | B16: 2 | C16: =IF(LEN(JD_INPUT!$B$12)<5,0,MIN(2,SUMPRODUCT(--ISNUMBER(SEARCH(TRIM(MID(SUBSTITUTE(KEYWORDS!$B$15,"|",REPT(" ",200)),(ROW(INDIRECT("1:"&KEYWORDS!$C$15))-1)*200+1,200)),JD_INPUT!$B$12))))) -> 1 | D16: =B16*C16 -> 2 | E16: =IF(C16=0,"No keyword match",IF(C16=1,"1 variant matched","2+ variants matched")) -> 1 variant matched | G16: =IF(C16=0,COUNTIF($C$4:C16,0),"") | H16: =IF(D16=0,REPT("░",20),REPT("█",MIN(20,D16*5))&REPT("░",MAX(0,20-MIN(20,D16*5)))) -> ██████████░░░░░░░░░░
A17: Operating model transformation | B17: 2 | C17: =IF(LEN(JD_INPUT!$B$12)<5,0,MIN(2,SUMPRODUCT(--ISNUMBER(SEARCH(TRIM(MID(SUBSTITUTE(KEYWORDS!$B$16,"|",REPT(" ",200)),(ROW(INDIRECT("1:"&KEYWORDS!$C$16))-1)*200+1,200)),JD_INPUT!$B$12))))) -> 1 | D17: =B17*C17 -> 2 | E17: =IF(C17=0,"No keyword match",IF(C17=1,"1 variant matched","2+ variants matched")) -> 1 variant matched | G17: =IF(C17=0,COUNTIF($C$4:C17,0),"") | H17: =IF(D17=0,REPT("░",20),REPT("█",MIN(20,D17*5))&REPT("░",MAX(0,20-MIN(20,D17*5)))) -> ██████████░░░░░░░░░░
A18: Cross-functional leadership | B18: 2 | C18: =IF(LEN(JD_INPUT!$B$12)<5,0,MIN(2,SUMPRODUCT(--ISNUMBER(SEARCH(TRIM(MID(SUBSTITUTE(KEYWORDS!$B$17,"|",REPT(" ",200)),(ROW(INDIRECT("1:"&KEYWORDS!$C$17))-1)*200+1,200)),JD_INPUT!$B$12))))) -> 1 | D18: =B18*C18 -> 2 | E18: =IF(C18=0,"No keyword match",IF(C18=1,"1 variant matched","2+ variants matched")) -> 1 variant matched | G18: =IF(C18=0,COUNTIF($C$4:C18,0),"") | H18: =IF(D18=0,REPT("░",20),REPT("█",MIN(20,D18*5))&REPT("░",MAX(0,20-MIN(20,D18*5)))) -> ██████████░░░░░░░░░░
A19: TOTAL KEYWORD SCORE | D19: =SUM(D4:D18) -> 12 | H19: =IF(D19=0,"⏳ Waiting for JD",REPT("█",MIN(30,D19))&" ("&D19&"/30)") -> ████████████ (12/30)
H20: █████ Strong (4) ██░░░ Partial (2) ░░░░░ Missing (0)
A21: Additional Scoring Factors (Rate 0-5)
A22: Responsibility Pattern Match (0-5) | D22: =MIN(5,IF(ISNUMBER(SEARCH("ai transformation",JD_INPUT!$B$12)),1,0)+IF(ISNUMBER(SEARCH("digital transformation",JD_INPUT!$B$12)),1,0)+IF(ISNUMBER(SEARCH("automation",JD_INPUT!$B$12)),1,0)+IF(ISNUMBER(SEARCH("modernization",JD_INPUT!$B$12)),1,0)+IF(ISNUMBER(SEARCH("innovation",JD_INPUT!$B$12)),1,0)) -> 1 | E22: How well does the JD's responsibilities align with AI Transformation role pattern?
A23: Company Match (0-5) | D23: =MIN(5,IF(ISNUMBER(SEARCH("ai",JD_INPUT!$B$12)),1,0)+IF(ISNUMBER(SEARCH("transformation",JD_INPUT!$B$12)),1,0)+IF(ISNUMBER(SEARCH("digital",JD_INPUT!$B$12)),1,0)+IF(ISNUMBER(SEARCH("consulting",JD_INPUT!$B$12)),1,0)+IF(ISNUMBER(SEARCH("strategy",JD_INPUT!$B$12)),1,0)) -> 4 | E23: Is the company AI-focused, transformation-led, or consulting-style?
A24: Red Flag Penalty (0-5) | D24: =MIN(5,IF(ISNUMBER(SEARCH("python",JD_INPUT!$B$12)),1,0)+IF(ISNUMBER(SEARCH("tensorflow",JD_INPUT!$B$12)),1,0)+IF(ISNUMBER(SEARCH("pytorch",JD_INPUT!$B$12)),1,0)+IF(ISNUMBER(SEARCH("data scientist",JD_INPUT!$B$12)),1,0)+IF(ISNUMBER(SEARCH("ml engineer",JD_INPUT!$B$12)),1,0)) -> 0 | E24: Penalty if JD requires deep hands-on ML/data science engineering
A26: FINAL SCORE | D26: =D19+D22+D23-D24 -> 17
A28: Key Gaps / Suggested Edits
A30: TOP MISSING KEYWORDS
A31: Rank | B31: Missing Keyword | C31: Weight | D31: Boost | E31: Action
A32: 1 | B32: =IFERROR(INDEX($A$4:$A$18,MATCH(1,$G$4:$G$18,0)),"All matched") -> AI transformation | C32: =IFERROR(VLOOKUP(B32,$A$4:$B$18,2,FALSE),"-") -> 2 | D32: =IF(ISNUMBER(C32),"+"&(C32*2)&" pts","-") -> +4 pts | E32: ="Add a bullet mentioning: "&B32 -> Add a bullet mentioning: AI transformation
A33: 2 | B33: =IFERROR(INDEX($A$4:$A$18,MATCH(2,$G$4:$G$18,0)),"All matched") -> Digital transformation | C33: =IFERROR(VLOOKUP(B33,$A$4:$B$18,2,FALSE),"-") -> 2 | D33: =IF(ISNUMBER(C33),"+"&(C33*2)&" pts","-") -> +4 pts | E33: ="Add a bullet mentioning: "&B33 -> Add a bullet mentioning: Digital transformation
A34: 3 | B34: =IFERROR(INDEX($A$4:$A$18,MATCH(3,$G$4:$G$18,0)),"All matched") -> Generative AI / GenAI | C34: =IFERROR(VLOOKUP(B34,$A$4:$B$18,2,FALSE),"-") -> 2 | D34: =IF(ISNUMBER(C34),"+"&(C34*2)&" pts","-") -> +4 pts | E34: ="Add a bullet mentioning: "&B34 -> Add a bullet mentioning: Generative AI / GenAI
A35: 4 | B35: =IFERROR(INDEX($A$4:$A$18,MATCH(4,$G$4:$G$18,0)),"All matched") -> Intelligent automation | C35: =IFERROR(VLOOKUP(B35,$A$4:$B$18,2,FALSE),"-") -> 2 | D35: =IF(ISNUMBER(C35),"+"&(C35*2)&" pts","-") -> +4 pts | E35: ="Add a bullet mentioning: "&B35 -> Add a bullet mentioning: Intelligent automation
A36: 5 | B36: =IFERROR(INDEX($A$4:$A$18,MATCH(5,$G$4:$G$18,0)),"All matched") -> AI adoption / AI strategy | C36: =IFERROR(VLOOKUP(B36,$A$4:$B$18,2,FALSE),"-") -> 2 | D36: =IF(ISNUMBER(C36),"+"&(C36*2)&" pts","-") -> +4 pts | E36: ="Add a bullet mentioning: "&B36 -> Add a bullet mentioning: AI adoption / AI strategy

Sheet TPM_SCORE
A1: Technical Program Manager - Scoring
A3: Keyword / Theme | B3: Weight | C3: Auto Score (0,1,2) | D3: Weighted Score | E3: Notes | H3: Contribution
A4: Technical program management | B4: 2 | C4: =IF(LEN(JD_INPUT!$B$12)<5,0,MIN(2,SUMPRODUCT(--ISNUMBER(SEARCH(TRIM(MID(SUBSTITUTE(KEYWORDS!$B$18,"|",REPT(" ",200)),(ROW(INDIRECT("1:"&KEYWORDS!$C$18))-1)*200+1,200)),JD_INPUT!$B$12))))) -> 0 | D4: =B4*C4 -> 0 | E4: =IF(C4=0,"No keyword match",IF(C4=1,"1 variant matched","2+ variants matched")) -> No keyword match | G4: =IF(C4=0,COUNTIF($C$4:C4,0),"") -> 1 | H4: =IF(D4=0,REPT("░",20),REPT("█",MIN(20,D4*5))&REPT("░",MAX(0,20-MIN(20,D4*5)))) -> ░░░░░░░░░░░░░░░░░░░░
A5: Program delivery | B5: 2 | C5: =IF(LEN(JD_INPUT!$B$12)<5,0,MIN(2,SUMPRODUCT(--ISNUMBER(SEARCH(TRIM(MID(SUBSTITUTE(KEYWORDS!$B$19,"|",REPT(" ",200)),(ROW(INDIRECT("1:"&KEYWORDS!$C$19))-1)*200+1,200)),JD_INPUT!$B$12))))) -> 0 | D5: =B5*C5 -> 0 | E5: =IF(C5=0,"No keyword match",IF(C5=1,"1 variant matched","2+ variants matched")) -> No keyword match | G5: =IF(C5=0,COUNTIF($C$4:C5,0),"") -> 2 | H5: =IF(D5=0,REPT("░",20),REPT("█",MIN(20,D5*5))&REPT("░",MAX(0,20-MIN(20,D5*5)))) -> ░░░░░░░░░░░░░░░░░░░░
A6: Roadmap execution | B6: 2 | C6: =IF(LEN(JD_INPUT!$B$12)<5,0,MIN(2,SUMPRODUCT(--ISNUMBER(SEARCH(TRIM(MID(SUBSTITUTE(KEYWORDS!$B$20,"|",REPT(" ",200)),(ROW(INDIRECT("1:"&KEYWORDS!$C$20))-1)*200+1,200)),JD_INPUT!$B$12))))) -> 1 | D6: =B6*C6 -> 2 | E6: =IF(C6=0,"No keyword match",IF(C6=1,"1 variant matched","2+ variants matched")) -> 1 variant matched | G6: =IF(C6=0,COUNTIF($C$4:C6,0),"") | H6: =IF(D6=0,REPT("░",20),REPT("█",MIN(20,D6*5))&REPT("░",MAX(0,20-MIN(20,D6*5)))) -> ██████████░░░░░░░░░░
A7: Cross-functional leadership | B7: 2 | C7: =IF(LEN(JD_INPUT!$B$12)<5,0,MIN(2,SUMPRODUCT(--ISNUMBER(SEARCH(TRIM(MID(SUBSTITUTE(KEYWORDS!$B$21,"|",REPT(" ",200)),(ROW(INDIRECT("1:"&KEYWORDS!$C$21))-1)*200+1,200)),JD_INPUT!$B$12))))) -> 1 | D7: =B7*C7 -> 2 | E7: =IF(C7=0,"No keyword match",IF(C7=1,"1 variant matched","2+ variants matched")) -> 1 variant matched | G7: =IF(C7=0,COUNTIF($C$4:C7,0),"") | H7: =IF(D7=0,REPT("░",20),REPT("█",MIN(20,D7*5))&REPT("░",MAX(0,20-MIN(20,D7*5)))) -> ██████████░░░░░░░░░░
A8: Stakeholder management | B8: 2 | C8: =IF(LEN(JD_INPUT!$B$12)<5,0,MIN(2,SUMPRODUCT(--ISNUMBER(SEARCH(TRIM(MID(SUBSTITUTE(KEYWORDS!$B$22,"|",REPT(" ",200)),(ROW(INDIRECT("1:"&KEYWORDS!$C$22))-1)*200+1,200)),JD_INPUT!$B$12))))) -> 1 | D8: =B8*C8 -> 2 | E8: =IF(C8=0,"No keyword match",IF(C8=1,"1 variant matched","2+ variants matched")) -> 1 variant matched | G8: =IF(C8=0,COUNTIF($C$4:C8,0),"") | H8: =IF(D8=0,REPT("░",20),REPT("█",MIN(20,D8*5))&REPT("░",MAX(0,20-MIN(20,D8*5)))) -> ██████████░░░░░░░░░░
A9: Risk management | B9: 2 | C9: =IF(LEN(JD_INPUT!$B$12)<5,0,MIN(2,SUMPRODUCT(--ISNUMBER(SEARCH(TRIM(MID(SUBSTITUTE(KEYWORDS!$B$23,"|",REPT(" ",200)),(ROW(INDIRECT("1:"&KEYWORDS!$C$23))-1)*200+1,200)),JD_INPUT!$B$12))))) -> 0 | D9: =B9*C9 -> 0 | E9: =IF(C9=0,"No keyword match",IF(C9=1,"1 variant matched","2+ variants matched")) -> No keyword match | G9: =IF(C9=0,COUNTIF($C$4:C9,0),"") -> 3 | H9: =IF(D9=0,REPT("░",20),REPT("█",MIN(20,D9*5))&REPT("░",MAX(0,20-MIN(20,D9*5)))) -> ░░░░░░░░░░░░░░░░░░░░
A10: Dependency management | B10: 2 | C10: =IF(LEN(JD_INPUT!$B$12)<5,0,MIN(2,SUMPRODUCT(--ISNUMBER(SEARCH(TRIM(MID(SUBSTITUTE(KEYWORDS!$B$24,"|",REPT(" ",200)),(ROW(INDIRECT("1:"&KEYWORDS!$C$24))-1)*200+1,200)),JD_INPUT!$B$12))))) -> 1 | D10: =B10*C10 -> 2 | E10: =IF(C10=0,"No keyword match",IF(C10=1,"1 variant matched","2+ variants matched")) -> 1 variant matched | G10: =IF(C10=0,COUNTIF($C$4:C10,0),"") | H10: =IF(D10=0,REPT("░",20),REPT("█",MIN(20,D10*5))&REPT("░",MAX(0,20-MIN(20,D10*5)))) -> ██████████░░░░░░░░░░
A11: Change management | B11: 2 | C11: =IF(LEN(JD_INPUT!$B$12)<5,0,MIN(2,SUMPRODUCT(--ISNUMBER(SEARCH(TRIM(MID(SUBSTITUTE(KEYWORDS!$B$25,"|",REPT(" ",200)),(ROW(INDIRECT("1:"&KEYWORDS!$C$25))-1)*200+1,200)),JD_INPUT!$B$12))))) -> 0 | D11: =B11*C11 -> 0 | E11: =IF(C11=0,"No keyword match",IF(C11=1,"1 variant matched","2+ variants matched")) -> No keyword match | G11: =IF(C11=0,COUNTIF($C$4:C11,0),"") -> 4 | H11: =IF(D11=0,REPT("░",20),REPT("█",MIN(20,D11*5))&REPT("░",MAX(0,20-MIN(20,D11*5)))) -> ░░░░░░░░░░░░░░░░░░░░
A12: Release management | B12: 2 | C12: =IF(LEN(JD_INPUT!$B$12)<5,0,MIN(2,SUMPRODUCT(--ISNUMBER(SEARCH(TRIM(MID(SUBSTITUTE(KEYWORDS!$B$26,"|",REPT(" ",200)),(ROW(INDIRECT("1:"&KEYWORDS!$C$26))-1)*200+1,200)),JD_INPUT!$B$12))))) -> 0 | D12: =B12*C12 -> 0 | E12: =IF(C12=0,"No keyword match",IF(C12=1,"1 variant matched","2+ variants matched")) -> No keyword match | G12: =IF(C12=0,COUNTIF($C$4:C12,0),"") -> 5 | H12: =IF(D12=0,REPT("░",20),REPT("█",MIN(20,D12*5))&REPT("░",MAX(0,20-MIN(20,D12*5)))) -> ░░░░░░░░░░░░░░░░░░░░
A13: SDLC / Agile / Waterfall | B13: 2 | C13: =IF(LEN(JD_INPUT!$B$12)<5,0,MIN(2,SUMPRODUCT(--ISNUMBER(SEARCH(TRIM(MID(SUBSTITUTE(KEYWORDS!$B$27,"|",REPT(" ",200)),(ROW(INDIRECT("1:"&KEYWORDS!$C$27))-1)*200+1,200)),JD_INPUT!$B$12))))) -> 1 | D13: =B13*C13 -> 2 | E13: =IF(C13=0,"No keyword match",IF(C13=1,"1 variant matched","2+ variants matched")) -> 1 variant matched | G13: =IF(C13=0,COUNTIF($C$4:C13,0),"") | H13: =IF(D13=0,REPT("░",20),REPT("█",MIN(20,D13*5))&REPT("░",MAX(0,20-MIN(20,D13*5)))) -> ██████████░░░░░░░░░░
A14: Enterprise systems | B14: 2 | C14: =IF(LEN(JD_INPUT!$B$12)<5,0,MIN(2,SUMPRODUCT(--ISNUMBER(SEARCH(TRIM(MID(SUBSTITUTE(KEYWORDS!$B$28,"|",REPT(" ",200)),(ROW(INDIRECT("1:"&KEYWORDS!$C$28))-1)*200+1,200)),JD_INPUT!$B$12))))) -> 2 | D14: =B14*C14 -> 4 | E14: =IF(C14=0,"No keyword match",IF(C14=1,"1 variant matched","2+ variants matched")) -> 2+ variants matched | G14: =IF(C14=0,COUNTIF($C$4:C14,0),"") | H14: =IF(D14=0,REPT("░",20),REPT("█",MIN(20,D14*5))&REPT("░",MAX(0,20-MIN(20,D14*5)))) -> ████████████████████
A15: Cloud migration | B15: 2 | C15: =IF(LEN(JD_INPUT!$B$12)<5,0,MIN(2,SUMPRODUCT(--ISNUMBER(SEARCH(TRIM(MID(SUBSTITUTE(KEYWORDS!$B$29,"|",REPT(" ",200)),(ROW(INDIRECT("1:"&KEYWORDS!$C$29))-1)*200+1,200)),JD_INPUT!$B$12))))) -> 0 | D15: =B15*C15 -> 0 | E15: =IF(C15=0,"No keyword match",IF(C15=1,"1 variant matched","2+ variants matched")) -> No keyword match | G15: =IF(C15=0,COUNTIF($C$4:C15,0),"") -> 6 | H15: =IF(D15=0,REPT("░",20),REPT("█",MIN(20,D15*5))&REPT("░",MAX(0,20-MIN(20,D15*5)))) -> ░░░░░░░░░░░░░░░░░░░░
A16: Datacenter migration | B16: 2 | C16: =IF(LEN(JD_INPUT!$B$12)<5,0,MIN(2,SUMPRODUCT(--ISNUMBER(SEARCH(TRIM(MID(SUBSTITUTE(KEYWORDS!$B$30,"|",REPT(" ",200)),(ROW(INDIRECT("1:"&KEYWORDS!$C$30))-1)*200+1,200)),JD_INPUT!$B$12))))) -> 0 | D16: =B16*C16 -> 0 | E16: =IF(C16=0,"No keyword match",IF(C16=1,"1 variant matched","2+ variants matched")) -> No keyword match | G16: =IF(C16=0,COUNTIF($C$4:C16,0),"") -> 7 | H16: =IF(D16=0,REPT("░",20),REPT("█",MIN(20,D16*5))&REPT("░",MAX(0,20-MIN(20,D16*5)))) -> ░░░░░░░░░░░░░░░░░░░░
A17: High availability / reliability | B17: 2 | C17: =IF(LEN(JD_INPUT!$B$12)<5,0,MIN(2,SUMPRODUCT(--ISNUMBER(SEARCH(TRIM(MID(SUBSTITUTE(KEYWORDS!$B$31,"|",REPT(" ",200)),(ROW(INDIRECT("1:"&KEYWORDS!$C$31))-1)*200+1,200)),JD_INPUT!$B$12))))) -> 1 | D17: =B17*C17 -> 2 | E17: =IF(C17=0,"No keyword match",IF(C17=1,"1 variant matched","2+ variants matched")) -> 1 variant matched | G17: =IF(C17=0,COUNTIF($C$4:C17,0),"") | H17: =IF(D17=0,REPT("░",20),REPT("█",MIN(20,D17*5))&REPT("░",MAX(0,20-MIN(20,D17*5)))) -> ██████████░░░░░░░░░░
A18: Vendor management | B18: 2 | C18: =IF(LEN(JD_INPUT!$B$12)<5,0,MIN(2,SUMPRODUCT(--ISNUMBER(SEARCH(TRIM(MID(SUBSTITUTE(KEYWORDS!$B$32,"|",REPT(" ",200)),(ROW(INDIRECT("1:"&KEYWORDS!$C$32))-1)*200+1,200)),JD_INPUT!$B$12))))) -> 0 | D18: =B18*C18 -> 0 | E18: =IF(C18=0,"No keyword match",IF(C18=1,"1 variant matched","2+ variants matched")) -> No keyword match | G18: =IF(C18=0,COUNTIF($C$4:C18,0),"") -> 8 | H18: =IF(D18=0,REPT("░",20),REPT("█",MIN(20,D18*5))&REPT("░",MAX(0,20-MIN(20,D18*5)))) -> ░░░░░░░░░░░░░░░░░░░░
A19: TOTAL KEYWORD SCORE | D19: =SUM(D4:D18) -> 16 | H19: =IF(D19=0,"⏳ Waiting for JD",REPT("█",MIN(30,D19))&" ("&D19&"/30)") -> ████████████████ (16/30)
H20: █████ Strong (4) ██░░░ Partial (2) ░░░░░ Missing (0)
A21: Additional Scoring Factors (Rate 0-5)
A22: Responsibility Pattern Match (0-5) | D22: =MIN(5,IF(ISNUMBER(SEARCH("program",JD_INPUT!$B$12)),1,0)+IF(ISNUMBER(SEARCH("roadmap",JD_INPUT!$B$12)),1,0)+IF(ISNUMBER(SEARCH("delivery",JD_INPUT!$B$12)),1,0)+IF(ISNUMBER(SEARCH("stakeholders",JD_INPUT!$B$12)),1,0)+IF(ISNUMBER(SEARCH("release",JD_INPUT!$B$12)),1,0)) -> 3 | E22: How well does the JD align with TPM responsibility pattern (program delivery, governance)?
A23: Company Match (0-5) | D23: =MIN(5,IF(ISNUMBER(SEARCH("product",JD_INPUT!$B$12)),1,0)+IF(ISNUMBER(SEARCH("platform",JD_INPUT!$B$12)),1,0)+IF(ISNUMBER(SEARCH("engineering",JD_INPUT!$B$12)),1,0)+IF(ISNUMBER(SEARCH("enterprise",JD_INPUT!$B$12)),1,0)+IF(ISNUMBER(SEARCH("gcc",JD_INPUT!$B$12)),1,0)) -> 3 | E23: Is the company a product company, GCC, or consulting tech delivery firm?
A24: Red Flag Penalty (0-5) | D24: =MIN(5,IF(ISNUMBER(SEARCH("helpdesk",JD_INPUT!$B$12)),1,0)+IF(ISNUMBER(SEARCH("l1 support",JD_INPUT!$B$12)),1,0)+IF(ISNUMBER(SEARCH("call center",JD_INPUT!$B$12)),1,0)+IF(ISNUMBER(SEARCH("desktop support",JD_INPUT!$B$12)),1,0)+IF(ISNUMBER(SEARCH("field support",JD_INPUT!$B$12)),1,0)) -> 0 | E24: Penalty if JD is mainly operations/support with no program ownership
A26: FINAL SCORE | D26: =D19+D22+D23-D24 -> 22
A28: Key Gaps / Suggested Edits
A30: TOP MISSING KEYWORDS
A31: Rank | B31: Missing Keyword | C31: Weight | D31: Boost | E31: Action
A32: 1 | B32: =IFERROR(INDEX($A$4:$A$18,MATCH(1,$G$4:$G$18,0)),"All matched") -> Technical program management | C32: =IFERROR(VLOOKUP(B32,$A$4:$B$18,2,FALSE),"-") -> 2 | D32: =IF(ISNUMBER(C32),"+"&(C32*2)&" pts","-") -> +4 pts | E32: ="Add a bullet mentioning: "&B32 -> Add a bullet mentioning: Technical program management
A33: 2 | B33: =IFERROR(INDEX($A$4:$A$18,MATCH(2,$G$4:$G$18,0)),"All matched") -> Program delivery | C33: =IFERROR(VLOOKUP(B33,$A$4:$B$18,2,FALSE),"-") -> 2 | D33: =IF(ISNUMBER(C33),"+"&(C33*2)&" pts","-") -> +4 pts | E33: ="Add a bullet mentioning: "&B33 -> Add a bullet mentioning: Program delivery
A34: 3 | B34: =IFERROR(INDEX($A$4:$A$18,MATCH(3,$G$4:$G$18,0)),"All matched") -> Risk management | C34: =IFERROR(VLOOKUP(B34,$A$4:$B$18,2,FALSE),"-") -> 2 | D34: =IF(ISNUMBER(C34),"+"&(C34*2)&" pts","-") -> +4 pts | E34: ="Add a bullet mentioning: "&B34 -> Add a bullet mentioning: Risk management
A35: 4 | B35: =IFERROR(INDEX($A$4:$A$18,MATCH(4,$G$4:$G$18,0)),"All matched") -> Change management | C35: =IFERROR(VLOOKUP(B35,$A$4:$B$18,2,FALSE),"-") -> 2 | D35: =IF(ISNUMBER(C35),"+"&(C35*2)&" pts","-") -> +4 pts | E35: ="Add a bullet mentioning: "&B35 -> Add a bullet mentioning: Change management
A36: 5 | B36: =IFERROR(INDEX($A$4:$A$18,MATCH(5,$G$4:$G$18,0)),"All matched") -> Release management | C36: =IFERROR(VLOOKUP(B36,$A$4:$B$18,2,FALSE),"-") -> 2 | D36: =IF(ISNUMBER(C36),"+"&(C36*2)&" pts","-") -> +4 pts | E36: ="Add a bullet mentioning: "&B36 -> Add a bullet mentioning: Release management

Sheet ITDM_SCORE
A1: IT Delivery Manager - Scoring
A3: Keyword / Theme | B3: Weight | C3: Auto Score (0,1,2) | D3: Weighted Score | E3: Notes | H3: Contribution
A4: IT delivery management | B4: 2 | C4: =IF(LEN(JD_INPUT!$B$12)<5,0,MIN(2,SUMPRODUCT(--ISNUMBER(SEARCH(TRIM(MID(SUBSTITUTE(KEYWORDS!$B$33,"|",REPT(" ",200)),(ROW(INDIRECT("1:"&KEYWORDS!$C$33))-1)*200+1,200)),JD_INPUT!$B$12))))) -> 0 | D4: =B4*C4 -> 0 | E4: =IF(C4=0,"No keyword match",IF(C4=1,"1 variant matched","2+ variants matched")) -> No keyword match | G4: =IF(C4=0,COUNTIF($C$4:C4,0),"") -> 1 | H4: =IF(D4=0,REPT("░",20),REPT("█",MIN(20,D4*5))&REPT("░",MAX(0,20-MIN(20,D4*5)))) -> ░░░░░░░░░░░░░░░░░░░░
A5: Service delivery | B5: 2 | C5: =IF(LEN(JD_INPUT!$B$12)<5,0,MIN(2,SUMPRODUCT(--ISNUMBER(SEARCH(TRIM(MID(SUBSTITUTE(KEYWORDS!$B$34,"|",REPT(" ",200)),(ROW(INDIRECT("1:"&KEYWORDS!$C$34))-1)*200+1,200)),JD_INPUT!$B$12))))) -> 0 | D5: =B5*C5 -> 0 | E5: =IF(C5=0,"No keyword match",IF(C5=1,"1 variant matched","2+ variants matched")) -> No keyword match | G5: =IF(C5=0,COUNTIF($C$4:C5,0),"") -> 2 | H5: =IF(D5=0,REPT("░",20),REPT("█",MIN(20,D5*5))&REPT("░",MAX(0,20-MIN(20,D5*5)))) -> ░░░░░░░░░░░░░░░░░░░░
A6: SLA management | B6: 2 | C6: =IF(LEN(JD_INPUT!$B$12)<5,0,MIN(2,SUMPRODUCT(--ISNUMBER(SEARCH(TRIM(MID(SUBSTITUTE(KEYWORDS!$B$35,"|",REPT(" ",200)),(ROW(INDIRECT("1:"&KEYWORDS!$C$35))-1)*200+1,200)),JD_INPUT!$B$12))))) -> 1 | D6: =B6*C6 -> 2 | E6: =IF(C6=0,"No keyword match",IF(C6=1,"1 variant matched","2+ variants matched")) -> 1 variant matched | G6: =IF(C6=0,COUNTIF($C$4:C6,0),"") | H6: =IF(D6=0,REPT("░",20),REPT("█",MIN(20,D6*5))&REPT("░",MAX(0,20-MIN(20,D6*5)))) -> ██████████░░░░░░░░░░
A7: Incident management | B7: 2 | C7: =IF(LEN(JD_INPUT!$B$12)<5,0,MIN(2,SUMPRODUCT(--ISNUMBER(SEARCH(TRIM(MID(SUBSTITUTE(KEYWORDS!$B$36,"|",REPT(" ",200)),(ROW(INDIRECT("1:"&KEYWORDS!$C$36))-1)*200+1,200)),JD_INPUT!$B$12))))) -> 0 | D7: =B7*C7 -> 0 | E7: =IF(C7=0,"No keyword match",IF(C7=1,"1 variant matched","2+ variants matched")) -> No keyword match | G7: =IF(C7=0,COUNTIF($C$4:C7,0),"") -> 3 | H7: =IF(D7=0,REPT("░",20),REPT("█",MIN(20,D7*5))&REPT("░",MAX(0,20-MIN(20,D7*5)))) -> ░░░░░░░░░░░░░░░░░░░░
A8: Problem management | B8: 2 | C8: =IF(LEN(JD_INPUT!$B$12)<5,0,MIN(2,SUMPRODUCT(--ISNUMBER(SEARCH(TRIM(MID(SUBSTITUTE(KEYWORDS!$B$37,"|",REPT(" ",200)),(ROW(INDIRECT("1:"&KEYWORDS!$C$37))-1)*200+1,200)),JD_INPUT!$B$12))))) -> 0 | D8: =B8*C8 -> 0 | E8: =IF(C8=0,"No keyword match",IF(C8=1,"1 variant matched","2+ variants matched")) -> No keyword match | G8: =IF(C8=0,COUNTIF($C$4:C8,0),"") -> 4 | H8: =IF(D8=0,REPT("░",20),REPT("█",MIN(20,D8*5))&REPT("░",MAX(0,20-MIN(20,D8*5)))) -> ░░░░░░░░░░░░░░░░░░░░
A9: Change management | B9: 2 | C9: =IF(LEN(JD_INPUT!$B$12)<5,0,MIN(2,SUMPRODUCT(--ISNUMBER(SEARCH(TRIM(MID(SUBSTITUTE(KEYWORDS!$B$38,"|",REPT(" ",200)),(ROW(INDIRECT("1:"&KEYWORDS!$C$38))-1)*200+1,200)),JD_INPUT!$B$12))))) -> 0 | D9: =B9*C9 -> 0 | E9: =IF(C9=0,"No keyword match",IF(C9=1,"1 variant matched","2+ variants matched")) -> No keyword match | G9: =IF(C9=0,COUNTIF($C$4:C9,0),"") -> 5 | H9: =IF(D9=0,REPT("░",20),REPT("█",MIN(20,D9*5))&REPT("░",MAX(0,20-MIN(20,D9*5)))) -> ░░░░░░░░░░░░░░░░░░░░
A10: Release management | B10: 2 | C10: =IF(LEN(JD_INPUT!$B$12)<5,0,MIN(2,SUMPRODUCT(--ISNUMBER(SEARCH(TRIM(MID(SUBSTITUTE(KEYWORDS!$B$39,"|",REPT(" ",200)),(ROW(INDIRECT("1:"&KEYWORDS!$C$39))-1)*200+1,200)),JD_INPUT!$B$12))))) -> 0 | D10: =B10*C10 -> 0 | E10: =IF(C10=0,"No keyword match",IF(C10=1,"1 variant matched","2+ variants matched")) -> No keyword match | G10: =IF(C10=0,COUNTIF($C$4:C10,0),"") -> 6 | H10: =IF(D10=0,REPT("░",20),REPT("█",MIN(20,D10*5))&REPT("░",MAX(0,20-MIN(20,D10*5)))) -> ░░░░░░░░░░░░░░░░░░░░
A11: ITIL | B11: 2 | C11: =IF(LEN(JD_INPUT!$B$12)<5,0,MIN(2,SUMPRODUCT(--ISNUMBER(SEARCH(TRIM(MID(SUBSTITUTE(KEYWORDS!$B$40,"|",REPT(" ",200)),(ROW(INDIRECT("1:"&KEYWORDS!$C$40))-1)*200+1,200)),JD_INPUT!$B$12))))) -> 0 | D11: =B11*C11 -> 0 | E11: =IF(C11=0,"No keyword match",IF(C11=1,"1 variant matched","2+ variants matched")) -> No keyword match | G11: =IF(C11=0,COUNTIF($C$4:C11,0),"") -> 7 | H11: =IF(D11=0,REPT("░",20),REPT("█",MIN(20,D11*5))&REPT("░",MAX(0,20-MIN(20,D11*5)))) -> ░░░░░░░░░░░░░░░░░░░░
A12: ServiceNow | B12: 2 | C12: =IF(LEN(JD_INPUT!$B$12)<5,0,MIN(2,SUMPRODUCT(--ISNUMBER(SEARCH(TRIM(MID(SUBSTITUTE(KEYWORDS!$B$41,"|",REPT(" ",200)),(ROW(INDIRECT("1:"&KEYWORDS!$C$41))-1)*200+1,200)),JD_INPUT!$B$12))))) -> 0 | D12: =B12*C12 -> 0 | E12: =IF(C12=0,"No keyword match",IF(C12=1,"1 variant matched","2+ variants matched")) -> No keyword match | G12: =IF(C12=0,COUNTIF($C$4:C12,0),"") -> 8 | H12: =IF(D12=0,REPT("░",20),REPT("█",MIN(20,D12*5))&REPT("░",MAX(0,20-MIN(20,D12*5)))) -> ░░░░░░░░░░░░░░░░░░░░
A13: Operations management | B13: 2 | C13: =IF(LEN(JD_INPUT!$B$12)<5,0,MIN(2,SUMPRODUCT(--ISNUMBER(SEARCH(TRIM(MID(SUBSTITUTE(KEYWORDS!$B$42,"|",REPT(" ",200)),(ROW(INDIRECT("1:"&KEYWORDS!$C$42))-1)*200+1,200)),JD_INPUT!$B$12))))) -> 0 | D13: =B13*C13 -> 0 | E13: =IF(C13=0,"No keyword match",IF(C13=1,"1 variant matched","2+ variants matched")) -> No keyword match | G13: =IF(C13=0,COUNTIF($C$4:C13,0),"") -> 9 | H13: =IF(D13=0,REPT("░",20),REPT("█",MIN(20,D13*5))&REPT("░",MAX(0,20-MIN(20,D13*5)))) -> ░░░░░░░░░░░░░░░░░░░░
A14: Production support | B14: 2 | C14: =IF(LEN(JD_INPUT!$B$12)<5,0,MIN(2,SUMPRODUCT(--ISNUMBER(SEARCH(TRIM(MID(SUBSTITUTE(KEYWORDS!$B$43,"|",REPT(" ",200)),(ROW(INDIRECT("1:"&KEYWORDS!$C$43))-1)*200+1,200)),JD_INPUT!$B$12))))) -> 0 | D14: =B14*C14 -> 0 | E14: =IF(C14=0,"No keyword match",IF(C14=1,"1 variant matched","2+ variants matched")) -> No keyword match | G14: =IF(C14=0,COUNTIF($C$4:C14,0),"") -> 10 | H14: =IF(D14=0,REPT("░",20),REPT("█",MIN(20,D14*5))&REPT("░",MAX(0,20-MIN(20,D14*5)))) -> ░░░░░░░░░░░░░░░░░░░░
A15: Platform availability / uptime | B15: 2 | C15: =IF(LEN(JD_INPUT!$B$12)<5,0,MIN(2,SUMPRODUCT(--ISNUMBER(SEARCH(TRIM(MID(SUBSTITUTE(KEYWORDS!$B$44,"|",REPT(" ",200)),(ROW(INDIRECT("1:"&KEYWORDS!$C$44))-1)*200+1,200)),JD_INPUT!$B$12))))) -> 1 | D15: =B15*C15 -> 2 | E15: =IF(C15=0,"No keyword match",IF(C15=1,"1 variant matched","2+ variants matched")) -> 1 variant matched | G15: =IF(C15=0,COUNTIF($C$4:C15,0),"") | H15: =IF(D15=0,REPT("░",20),REPT("█",MIN(20,D15*5))&REPT("░",MAX(0,20-MIN(20,D15*5)))) -> ██████████░░░░░░░░░░
A16: Stakeholder management | B16: 2 | C16: =IF(LEN(JD_INPUT!$B$12)<5,0,MIN(2,SUMPRODUCT(--ISNUMBER(SEARCH(TRIM(MID(SUBSTITUTE(KEYWORDS!$B$45,"|",REPT(" ",200)),(ROW(INDIRECT("1:"&KEYWORDS!$C$45))-1)*200+1,200)),JD_INPUT!$B$12))))) -> 0 | D16: =B16*C16 -> 0 | E16: =IF(C16=0,"No keyword match",IF(C16=1,"1 variant matched","2+ variants matched")) -> No keyword match | G16: =IF(C16=0,COUNTIF($C$4:C16,0),"") -> 11 | H16: =IF(D16=0,REPT("░",20),REPT("█",MIN(20,D16*5))&REPT("░",MAX(0,20-MIN(20,D16*5)))) -> ░░░░░░░░░░░░░░░░░░░░
A17: Service improvement | B17: 2 | C17: =IF(LEN(JD_INPUT!$B$12)<5,0,MIN(2,SUMPRODUCT(--ISNUMBER(SEARCH(TRIM(MID(SUBSTITUTE(KEYWORDS!$B$46,"|",REPT(" ",200)),(ROW(INDIRECT("1:"&KEYWORDS!$C$46))-1)*200+1,200)),JD_INPUT!$B$12))))) -> 1 | D17: =B17*C17 -> 2 | E17: =IF(C17=0,"No keyword match",IF(C17=1,"1 variant matched","2+ variants matched")) -> 1 variant matched | G17: =IF(C17=0,COUNTIF($C$4:C17,0),"") | H17: =IF(D17=0,REPT("░",20),REPT("█",MIN(20,D17*5))&REPT("░",MAX(0,20-MIN(20,D17*5)))) -> ██████████░░░░░░░░░░
A18: CRM support / cloud operations | B18: 2 | C18: =IF(LEN(JD_INPUT!$B$12)<5,0,MIN(2,SUMPRODUCT(--ISNUMBER(SEARCH(TRIM(MID(SUBSTITUTE(KEYWORDS!$B$47,"|",REPT(" ",200)),(ROW(INDIRECT("1:"&KEYWORDS!$C$47))-1)*200+1,200)),JD_INPUT!$B$12))))) -> 0 | D18: =B18*C18 -> 0 | E18: =IF(C18=0,"No keyword match",IF(C18=1,"1 variant matched","2+ variants matched")) -> No keyword match | G18: =IF(C18=0,COUNTIF($C$4:C18,0),"") -> 12 | H18: =IF(D18=0,REPT("░",20),REPT("█",MIN(20,D18*5))&REPT("░",MAX(0,20-MIN(20,D18*5)))) -> ░░░░░░░░░░░░░░░░░░░░
A19: TOTAL KEYWORD SCORE | D19: =SUM(D4:D18) -> 6 | H19: =IF(D19=0,"⏳ Waiting for JD",REPT("█",MIN(30,D19))&" ("&D19&"/30)") -> ██████ (6/30)
H20: █████ Strong (4) ██░░░ Partial (2) ░░░░░ Missing (0)
A21: Additional Scoring Factors (Rate 0-5)
A22: Responsibility Pattern Match (0-5) | D22: =MIN(5,IF(ISNUMBER(SEARCH("sla",JD_INPUT!$B$12)),1,0)+IF(ISNUMBER(SEARCH("itil",JD_INPUT!$B$12)),1,0)+IF(ISNUMBER(SEARCH("incident",JD_INPUT!$B$12)),1,0)+IF(ISNUMBER(SEARCH("change management",JD_INPUT!$B$12)),1,0)+IF(ISNUMBER(SEARCH("service delivery",JD_INPUT!$B$12)),1,0)) -> 1 | E22: How well does the JD align with IT Delivery / service operations pattern?
A23: Company Match (0-5) | D23: =MIN(5,IF(ISNUMBER(SEARCH("managed services",JD_INPUT!$B$12)),1,0)+IF(ISNUMBER(SEARCH("support",JD_INPUT!$B$12)),1,0)+IF(ISNUMBER(SEARCH("operations",JD_INPUT!$B$12)),1,0)+IF(ISNUMBER(SEARCH("msp",JD_INPUT!$B$12)),1,0)+IF(ISNUMBER(SEARCH("outsourcing",JD_INPUT!$B$12)),1,0)) -> 2 | E23: Is the company an IT services, managed services, or ops-heavy enterprise?
A24: Red Flag Penalty (0-5) | D24: =MIN(5,IF(ISNUMBER(SEARCH("ai strategy",JD_INPUT!$B$12)),1,0)+IF(ISNUMBER(SEARCH("innovation",JD_INPUT!$B$12)),1,0)+IF(ISNUMBER(SEARCH("transformation roadmap",JD_INPUT!$B$12)),1,0)+IF(ISNUMBER(SEARCH("genai",JD_INPUT!$B$12)),1,0)+IF(ISNUMBER(SEARCH("ai vision",JD_INPUT!$B$12)),1,0)) -> 0 | E24: Penalty if JD is mainly strategy/innovation/AI vision oriented
A26: FINAL SCORE | D26: =D19+D22+D23-D24 -> 9
A28: Key Gaps / Suggested Edits
A30: TOP MISSING KEYWORDS
A31: Rank | B31: Missing Keyword | C31: Weight | D31: Boost | E31: Action
A32: 1 | B32: =IFERROR(INDEX($A$4:$A$18,MATCH(1,$G$4:$G$18,0)),"All matched") -> IT delivery management | C32: =IFERROR(VLOOKUP(B32,$A$4:$B$18,2,FALSE),"-") -> 2 | D32: =IF(ISNUMBER(C32),"+"&(C32*2)&" pts","-") -> +4 pts | E32: ="Add a bullet mentioning: "&B32 -> Add a bullet mentioning: IT delivery management
A33: 2 | B33: =IFERROR(INDEX($A$4:$A$18,MATCH(2,$G$4:$G$18,0)),"All matched") -> Service delivery | C33: =IFERROR(VLOOKUP(B33,$A$4:$B$18,2,FALSE),"-") -> 2 | D33: =IF(ISNUMBER(C33),"+"&(C33*2)&" pts","-") -> +4 pts | E33: ="Add a bullet mentioning: "&B33 -> Add a bullet mentioning: Service delivery
A34: 3 | B34: =IFERROR(INDEX($A$4:$A$18,MATCH(3,$G$4:$G$18,0)),"All matched") -> Incident management | C34: =IFERROR(VLOOKUP(B34,$A$4:$B$18,2,FALSE),"-") -> 2 | D34: =IF(ISNUMBER(C34),"+"&(C34*2)&" pts","-") -> +4 pts | E34: ="Add a bullet mentioning: "&B34 -> Add a bullet mentioning: Incident management
A35: 4 | B35: =IFERROR(INDEX($A$4:$A$18,MATCH(4,$G$4:$G$18,0)),"All matched") -> Problem management | C35: =IFERROR(VLOOKUP(B35,$A$4:$B$18,2,FALSE),"-") -> 2 | D35: =IF(ISNUMBER(C35),"+"&(C35*2)&" pts","-") -> +4 pts | E35: ="Add a bullet mentioning: "&B35 -> Add a bullet mentioning: Problem management
A36: 5 | B36: =IFERROR(INDEX($A$4:$A$18,MATCH(5,$G$4:$G$18,0)),"All matched") -> Change management | C36: =IFERROR(VLOOKUP(B36,$A$4:$B$18,2,FALSE),"-") -> 2 | D36: =IF(ISNUMBER(C36),"+"&(C36*2)&" pts","-") -> +4 pts | E36: ="Add a bullet mentioning: "&B36 -> Add a bullet mentioning: Change management

Sheet PM_SCORE
A1: Product Manager - Scoring
A3: Keyword / Theme | B3: Weight | C3: Auto Score (0,1,2) | D3: Weighted Score | E3: Notes | H3: Contribution
A4: Product management | B4: 2 | C4: =IF(LEN(JD_INPUT!$B$12)<5,0,MIN(2,SUMPRODUCT(--ISNUMBER(SEARCH(TRIM(MID(SUBSTITUTE(KEYWORDS!$B$48,"|",REPT(" ",200)),(ROW(INDIRECT("1:"&KEYWORDS!$C$48))-1)*200+1,200)),JD_INPUT!$B$12))))) -> 0 | D4: =B4*C4 -> 0 | E4: =IF(C4=0,"No keyword match",IF(C4=1,"1 variant matched","2+ variants matched")) -> No keyword match | G4: =IF(C4=0,COUNTIF($C$4:C4,0),"") -> 1 | H4: =IF(D4=0,REPT("░",20),REPT("█",MIN(20,D4*5))&REPT("░",MAX(0,20-MIN(20,D4*5)))) -> ░░░░░░░░░░░░░░░░░░░░
A5: Product strategy | B5: 2 | C5: =IF(LEN(JD_INPUT!$B$12)<5,0,MIN(2,SUMPRODUCT(--ISNUMBER(SEARCH(TRIM(MID(SUBSTITUTE(KEYWORDS!$B$49,"|",REPT(" ",200)),(ROW(INDIRECT("1:"&KEYWORDS!$C$49))-1)*200+1,200)),JD_INPUT!$B$12))))) -> 0 | D5: =B5*C5 -> 0 | E5: =IF(C5=0,"No keyword match",IF(C5=1,"1 variant matched","2+ variants matched")) -> No keyword match | G5: =IF(C5=0,COUNTIF($C$4:C5,0),"") -> 2 | H5: =IF(D5=0,REPT("░",20),REPT("█",MIN(20,D5*5))&REPT("░",MAX(0,20-MIN(20,D5*5)))) -> ░░░░░░░░░░░░░░░░░░░░
A6: Product roadmap | B6: 2 | C6: =IF(LEN(JD_INPUT!$B$12)<5,0,MIN(2,SUMPRODUCT(--ISNUMBER(SEARCH(TRIM(MID(SUBSTITUTE(KEYWORDS!$B$50,"|",REPT(" ",200)),(ROW(INDIRECT("1:"&KEYWORDS!$C$50))-1)*200+1,200)),JD_INPUT!$B$12))))) -> 1 | D6: =B6*C6 -> 2 | E6: =IF(C6=0,"No keyword match",IF(C6=1,"1 variant matched","2+ variants matched")) -> 1 variant matched | G6: =IF(C6=0,COUNTIF($C$4:C6,0),"") | H6: =IF(D6=0,REPT("░",20),REPT("█",MIN(20,D6*5))&REPT("░",MAX(0,20-MIN(20,D6*5)))) -> ██████████░░░░░░░░░░
A7: Customer discovery | B7: 2 | C7: =IF(LEN(JD_INPUT!$B$12)<5,0,MIN(2,SUMPRODUCT(--ISNUMBER(SEARCH(TRIM(MID(SUBSTITUTE(KEYWORDS!$B$51,"|",REPT(" ",200)),(ROW(INDIRECT("1:"&KEYWORDS!$C$51))-1)*200+1,200)),JD_INPUT!$B$12))))) -> 0 | D7: =B7*C7 -> 0 | E7: =IF(C7=0,"No keyword match",IF(C7=1,"1 variant matched","2+ variants matched")) -> No keyword match | G7: =IF(C7=0,COUNTIF($C$4:C7,0),"") -> 3 | H7: =IF(D7=0,REPT("░",20),REPT("█",MIN(20,D7*5))&REPT("░",MAX(0,20-MIN(20,D7*5)))) -> ░░░░░░░░░░░░░░░░░░░░
A8: User research | B8: 2 | C8: =IF(LEN(JD_INPUT!$B$12)<5,0,MIN(2,SUMPRODUCT(--ISNUMBER(SEARCH(TRIM(MID(SUBSTITUTE(KEYWORDS!$B$52,"|",REPT(" ",200)),(ROW(INDIRECT("1:"&KEYWORDS!$C$52))-1)*200+1,200)),JD_INPUT!$B$12))))) -> 0 | D8: =B8*C8 -> 0 | E8: =IF(C8=0,"No keyword match",IF(C8=1,"1 variant matched","2+ variants matched")) -> No keyword match | G8: =IF(C8=0,COUNTIF($C$4:C8,0),"") -> 4 | H8: =IF(D8=0,REPT("░",20),REPT("█",MIN(20,D8*5))&REPT("░",MAX(0,20-MIN(20,D8*5)))) -> ░░░░░░░░░░░░░░░░░░░░
A9: Product analytics | B9: 2 | C9: =IF(LEN(JD_INPUT!$B$12)<5,0,MIN(2,SUMPRODUCT(--ISNUMBER(SEARCH(TRIM(MID(SUBSTITUTE(KEYWORDS!$B$53,"|",REPT(" ",200)),(ROW(INDIRECT("1:"&KEYWORDS!$C$53))-1)*200+1,200)),JD_INPUT!$B$12))))) -> 0 | D9: =B9*C9 -> 0 | E9: =IF(C9=0,"No keyword match",IF(C9=1,"1 variant matched","2+ variants matched")) -> No keyword match | G9: =IF(C9=0,COUNTIF($C$4:C9,0),"") -> 5 | H9: =IF(D9=0,REPT("░",20),REPT("█",MIN(20,D9*5))&REPT("░",MAX(0,20-MIN(20,D9*5)))) -> ░░░░░░░░░░░░░░░░░░░░
A10: A/B testing / experimentation | B10: 2 | C10: =IF(LEN(JD_INPUT!$B$12)<5,0,MIN(2,SUMPRODUCT(--ISNUMBER(SEARCH(TRIM(MID(SUBSTITUTE(KEYWORDS!$B$54,"|",REPT(" ",200)),(ROW(INDIRECT("1:"&KEYWORDS!$C$54))-1)*200+1,200)),JD_INPUT!$B$12))))) -> 0 | D10: =B10*C10 -> 0 | E10: =IF(C10=0,"No keyword match",IF(C10=1,"1 variant matched","2+ variants matched")) -> No keyword match | G10: =IF(C10=0,COUNTIF($C$4:C10,0),"") -> 6 | H10: =IF(D10=0,REPT("░",20),REPT("█",MIN(20,D10*5))&REPT("░",MAX(0,20-MIN(20,D10*5)))) -> ░░░░░░░░░░░░░░░░░░░░
A11: Product-market fit | B11: 2 | C11: =IF(LEN(JD_INPUT!$B$12)<5,0,MIN(2,SUMPRODUCT(--ISNUMBER(SEARCH(TRIM(MID(SUBSTITUTE(KEYWORDS!$B$55,"|",REPT(" ",200)),(ROW(INDIRECT("1:"&KEYWORDS!$C$55))-1)*200+1,200)),JD_INPUT!$B$12))))) -> 0 | D11: =B11*C11 -> 0 | E11: =IF(C11=0,"No keyword match",IF(C11=1,"1 variant matched","2+ variants matched")) -> No keyword match | G11: =IF(C11=0,COUNTIF($C$4:C11,0),"") -> 7 | H11: =IF(D11=0,REPT("░",20),REPT("█",MIN(20,D11*5))&REPT("░",MAX(0,20-MIN(20,D11*5)))) -> ░░░░░░░░░░░░░░░░░░░░
A12: Product launch / go-to-market | B12: 2 | C12: =IF(LEN(JD_INPUT!$B$12)<5,0,MIN(2,SUMPRODUCT(--ISNUMBER(SEARCH(TRIM(MID(SUBSTITUTE(KEYWORDS!$B$56,"|",REPT(" ",200)),(ROW(INDIRECT("1:"&KEYWORDS!$C$56))-1)*200+1,200)),JD_INPUT!$B$12))))) -> 2 | D12: =B12*C12 -> 4 | E12: =IF(C12=0,"No keyword match",IF(C12=1,"1 variant matched","2+ variants matched")) -> 2+ variants matched | G12: =IF(C12=0,COUNTIF($C$4:C12,0),"") | H12: =IF(D12=0,REPT("░",20),REPT("█",MIN(20,D12*5))&REPT("░",MAX(0,20-MIN(20,D12*5)))) -> ████████████████████
A13: Stakeholder management (PM) | B13: 2 | C13: =IF(LEN(JD_INPUT!$B$12)<5,0,MIN(2,SUMPRODUCT(--ISNUMBER(SEARCH(TRIM(MID(SUBSTITUTE(KEYWORDS!$B$57,"|",REPT(" ",200)),(ROW(INDIRECT("1:"&KEYWORDS!$C$57))-1)*200+1,200)),JD_INPUT!$B$12))))) -> 0 | D13: =B13*C13 -> 0 | E13: =IF(C13=0,"No keyword match",IF(C13=1,"1 variant matched","2+ variants matched")) -> No keyword match | G13: =IF(C13=0,COUNTIF($C$4:C13,0),"") -> 8 | H13: =IF(D13=0,REPT("░",20),REPT("█",MIN(20,D13*5))&REPT("░",MAX(0,20-MIN(20,D13*5)))) -> ░░░░░░░░░░░░░░░░░░░░
A14: Cross-functional leadership (PM) | B14: 2 | C14: =IF(LEN(JD_INPUT!$B$12)<5,0,MIN(2,SUMPRODUCT(--ISNUMBER(SEARCH(TRIM(MID(SUBSTITUTE(KEYWORDS!$B$58,"|",REPT(" ",200)),(ROW(INDIRECT("1:"&KEYWORDS!$C$58))-1)*200+1,200)),JD_INPUT!$B$12))))) -> 1 | D14: =B14*C14 -> 2 | E14: =IF(C14=0,"No keyword match",IF(C14=1,"1 variant matched","2+ variants matched")) -> 1 variant matched | G14: =IF(C14=0,COUNTIF($C$4:C14,0),"") | H14: =IF(D14=0,REPT("░",20),REPT("█",MIN(20,D14*5))&REPT("░",MAX(0,20-MIN(20,D14*5)))) -> ██████████░░░░░░░░░░
A15: Data-driven decisions | B15: 2 | C15: =IF(LEN(JD_INPUT!$B$12)<5,0,MIN(2,SUMPRODUCT(--ISNUMBER(SEARCH(TRIM(MID(SUBSTITUTE(KEYWORDS!$B$59,"|",REPT(" ",200)),(ROW(INDIRECT("1:"&KEYWORDS!$C$59))-1)*200+1,200)),JD_INPUT!$B$12))))) -> 0 | D15: =B15*C15 -> 0 | E15: =IF(C15=0,"No keyword match",IF(C15=1,"1 variant matched","2+ variants matched")) -> No keyword match | G15: =IF(C15=0,COUNTIF($C$4:C15,0),"") -> 9 | H15: =IF(D15=0,REPT("░",20),REPT("█",MIN(20,D15*5))&REPT("░",MAX(0,20-MIN(20,D15*5)))) -> ░░░░░░░░░░░░░░░░░░░░
A16: OKRs / KPIs | B16: 2 | C16: =IF(LEN(JD_INPUT!$B$12)<5,0,MIN(2,SUMPRODUCT(--ISNUMBER(SEARCH(TRIM(MID(SUBSTITUTE(KEYWORDS!$B$60,"|",REPT(" ",200)),(ROW(INDIRECT("1:"&KEYWORDS!$C$60))-1)*200+1,200)),JD_INPUT!$B$12))))) -> 0 | D16: =B16*C16 -> 0 | E16: =IF(C16=0,"No keyword match",IF(C16=1,"1 variant matched","2+ variants matched")) -> No keyword match | G16: =IF(C16=0,COUNTIF($C$4:C16,0),"") -> 10 | H16: =IF(D16=0,REPT("░",20),REPT("█",MIN(20,D16*5))&REPT("░",MAX(0,20-MIN(20,D16*5)))) -> ░░░░░░░░░░░░░░░░░░░░
A17: Agile / Scrum (PM) | B17: 2 | C17: =IF(LEN(JD_INPUT!$B$12)<5,0,MIN(2,SUMPRODUCT(--ISNUMBER(SEARCH(TRIM(MID(SUBSTITUTE(KEYWORDS!$B$61,"|",REPT(" ",200)),(ROW(INDIRECT("1:"&KEYWORDS!$C$61))-1)*200+1,200)),JD_INPUT!$B$12))))) -> 1 | D17: =B17*C17 -> 2 | E17: =IF(C17=0,"No keyword match",IF(C17=1,"1 variant matched","2+ variants matched")) -> 1 variant matched | G17: =IF(C17=0,COUNTIF($C$4:C17,0),"") | H17: =IF(D17=0,REPT("░",20),REPT("█",MIN(20,D17*5))&REPT("░",MAX(0,20-MIN(20,D17*5)))) -> ██████████░░░░░░░░░░
A18: SaaS / B2B product | B18: 2 | C18: =IF(LEN(JD_INPUT!$B$12)<5,0,MIN(2,SUMPRODUCT(--ISNUMBER(SEARCH(TRIM(MID(SUBSTITUTE(KEYWORDS!$B$62,"|",REPT(" ",200)),(ROW(INDIRECT("1:"&KEYWORDS!$C$62))-1)*200+1,200)),JD_INPUT!$B$12))))) -> 1 | D18: =B18*C18 -> 2 | E18: =IF(C18=0,"No keyword match",IF(C18=1,"1 variant matched","2+ variants matched")) -> 1 variant matched | G18: =IF(C18=0,COUNTIF($C$4:C18,0),"") | H18: =IF(D18=0,REPT("░",20),REPT("█",MIN(20,D18*5))&REPT("░",MAX(0,20-MIN(20,D18*5)))) -> ██████████░░░░░░░░░░
A19: TOTAL KEYWORD SCORE | D19: =SUM(D4:D18) -> 12 | H19: =IF(D19=0,"⏳ Waiting for JD",REPT("█",MIN(30,D19))&" ("&D19&"/30)") -> ████████████ (12/30)
H20: █████ Strong (4) ██░░░ Partial (2) ░░░░░ Missing (0)
A21: Additional Scoring Factors (Rate 0-5)
A22: Responsibility Pattern Match (0-5) | D22: =MIN(5,IF(ISNUMBER(SEARCH("product",JD_INPUT!$B$12)),1,0)+IF(ISNUMBER(SEARCH("roadmap",JD_INPUT!$B$12)),1,0)+IF(ISNUMBER(SEARCH("customer",JD_INPUT!$B$12)),1,0)+IF(ISNUMBER(SEARCH("user research",JD_INPUT!$B$12)),1,0)+IF(ISNUMBER(SEARCH("analytics",JD_INPUT!$B$12)),1,0)) -> 3 | E22: How well does the JD align with Product Management responsibilities?
A23: Company/Product Match (0-5) | D23: =MIN(5,IF(ISNUMBER(SEARCH("saas",JD_INPUT!$B$12)),1,0)+IF(ISNUMBER(SEARCH("b2b",JD_INPUT!$B$12)),1,0)+IF(ISNUMBER(SEARCH("b2c",JD_INPUT!$B$12)),1,0)+IF(ISNUMBER(SEARCH("platform",JD_INPUT!$B$12)),1,0)+IF(ISNUMBER(SEARCH("product-led",JD_INPUT!$B$12)),1,0)) -> 1 | E23: Is the company a product-led SaaS/tech company?
A24: Red Flag Penalty (0-5) | D24: =MIN(5,IF(ISNUMBER(SEARCH("software engineer",JD_INPUT!$B$12)),1,0)+IF(ISNUMBER(SEARCH("python",JD_INPUT!$B$12)),1,0)+IF(ISNUMBER(SEARCH("data scientist",JD_INPUT!$B$12)),1,0)+IF(ISNUMBER(SEARCH("service delivery",JD_INPUT!$B$12)),1,0)+IF(ISNUMBER(SEARCH("incident management",JD_INPUT!$B$12)),1,0)) -> 0 | E24: Penalty if JD is heavily technical IC or operations-focused
A26: FINAL SCORE | D26: =D19+D22+D23-D24 -> 16
A27: MATCH LEVEL | D27: =IF(D26>=32,"🟢 STRONG MATCH",IF(D26>=25,"🔵 GOOD MATCH",IF(D26>=18,"🟡 MODERATE MATCH","🔴 WEAK MATCH"))) -> 🔴 WEAK MATCH
A28: SCORE PROGRESS | D28: =REPT("█",MIN(40,D26))&REPT("░",MAX(0,40-MIN(40,D26))) -> ████████████████░░░░░░░░░░░░░░░░░░░░░░░░
A30: TOP MISSING KEYWORDS
A31: Rank | B31: Missing Keyword | C31: Weight | D31: Boost | E31: Action
A32: 1 | B32: =IFERROR(INDEX($A$4:$A$18,MATCH(1,$G$4:$G$18,0)),"All matched") -> Product management | C32: =IFERROR(VLOOKUP(B32,$A$4:$B$18,2,FALSE),"-") -> 2 | D32: =IF(ISNUMBER(C32),"+"&(C32*2)&" pts","-") -> +4 pts | E32: ="Add a bullet mentioning: "&B32 -> Add a bullet mentioning: Product management
A33: 2 | B33: =IFERROR(INDEX($A$4:$A$18,MATCH(2,$G$4:$G$18,0)),"All matched") -> Product strategy | C33: =IFERROR(VLOOKUP(B33,$A$4:$B$18,2,FALSE),"-") -> 2 | D33: =IF(ISNUMBER(C33),"+"&(C33*2)&" pts","-") -> +4 pts | E33: ="Add a bullet mentioning: "&B33 -> Add a bullet mentioning: Product strategy
A34: 3 | B34: =IFERROR(INDEX($A$4:$A$18,MATCH(3,$G$4:$G$18,0)),"All matched") -> Customer discovery | C34: =IFERROR(VLOOKUP(B34,$A$4:$B$18,2,FALSE),"-") -> 2 | D34: =IF(ISNUMBER(C34),"+"&(C34*2)&" pts","-") -> +4 pts | E34: ="Add a bullet mentioning: "&B34 -> Add a bullet mentioning: Customer discovery
A35: 4 | B35: =IFERROR(INDEX($A$4:$A$18,MATCH(4,$G$4:$G$18,0)),"All matched") -> User research | C35: =IFERROR(VLOOKUP(B35,$A$4:$B$18,2,FALSE),"-") -> 2 | D35: =IF(ISNUMBER(C35),"+"&(C35*2)&" pts","-") -> +4 pts | E35: ="Add a bullet mentioning: "&B35 -> Add a bullet mentioning: User research
A36: 5 | B36: =IFERROR(INDEX($A$4:$A$18,MATCH(5,$G$4:$G$18,0)),"All matched") -> Product analytics | C36: =IFERROR(VLOOKUP(B36,$A$4:$B$18,2,FALSE),"-") -> 2 | D36: =IF(ISNUMBER(C36),"+"&(C36*2)&" pts","-") -> +4 pts | E36: ="Add a bullet mentioning: "&B36 -> Add a bullet mentioning: Product analytics

Sheet KEYWORDS
A1: 🔑 KEYWORD SYNONYM BANK — Expanded (Tier & Track tagged)
A2: Keyword | B2: Synonyms | C2: Count | D2: Weight Tier | E2: Track
A3: AI transformation | B3: ai transformation|ai-led|ai driven|enterprise ai|ai modernization|ai adoption|ai enablement|ai-first|ai integration | C3: =LEN(B3)-LEN(SUBSTITUTE(B3,"|",""))+1 -> 9 | D3: Tier 1 | E3: AI
A4: Digital transformation | B4: digital transformation|digital modernization|digitalization|digital change|digital reinvention|business transformation|modernization program | C4: =LEN(B4)-LEN(SUBSTITUTE(B4,"|",""))+1 -> 7 | D4: Tier 2 | E4: AI
A5: Generative AI GenAI | B5: generative ai|genai|gen-ai|gen ai|llm|llms|large language model|chatgpt|gpt-4|gpt-5|claude|gemini|copilot|foundation model|prompt engineering|rag|retrieval augmented | C5: =LEN(B5)-LEN(SUBSTITUTE(B5,"|",""))+1 -> 17 | D5: Tier 1 | E5: AI
A6: Intelligent automation | B6: intelligent automation|hyperautomation|rpa|robotic process automation|workflow automation|uipath|blue prism|automation anywhere|process automation | C6: =LEN(B6)-LEN(SUBSTITUTE(B6,"|",""))+1 -> 9 | D6: Tier 2 | E6: AI
A7: AI strategy | B7: ai adoption|ai strategy|ai roadmap|ai vision|responsible ai|ai governance|ai ethics|ai policy|ai center of excellence|ai coe | C7: =LEN(B7)-LEN(SUBSTITUTE(B7,"|",""))+1 -> 10 | D7: Tier 1 | E7: AI
A8: Transformation roadmap | B8: transformation roadmap|modernization roadmap|target operating model|strategic roadmap|multi-year roadmap|transformation strategy|program roadmap | C8: =LEN(B8)-LEN(SUBSTITUTE(B8,"|",""))+1 -> 7 | D8: Tier 1 | E8: AI
A9: Enterprise modernization | B9: enterprise modernization|legacy modernization|platform modernization|application modernization|infrastructure modernization|mainframe modernization|technical debt | C9: =LEN(B9)-LEN(SUBSTITUTE(B9,"|",""))+1 -> 7 | D9: Tier 2 | E9: AI
A10: Change management AI | B10: change management|organizational change|adoption|change leadership|ocm|prosci|adkar|change adoption|change enablement | C10: =LEN(B10)-LEN(SUBSTITUTE(B10,"|",""))+1 -> 9 | D10: Tier 1 | E10: AI
A11: Stakeholder governance | B11: stakeholder|executive sponsor|governance|steering committee|c-suite|executive|senior leadership|board level|executive stakeholders | C11: =LEN(B11)-LEN(SUBSTITUTE(B11,"|",""))+1 -> 9 | D11: Tier 2 | E11: AI
A12: CRM transformation | B12: crm transformation|crm modernization|customer relationship|sales cloud|service cloud|customer experience|cx transformation | C12: =LEN(B12)-LEN(SUBSTITUTE(B12,"|",""))+1 -> 7 | D12: Tier 3 | E12: AI
A13: Salesforce Siebel ServiceNow | B13: salesforce|siebel|servicenow|sfdc|einstein|dynamics 365|hubspot|marketing cloud | C13: =LEN(B13)-LEN(SUBSTITUTE(B13,"|",""))+1 -> 8 | D13: Tier 3 | E13: AI
A14: Cloud migration AI | B14: cloud migration|cloud transition|aws|azure|gcp|google cloud|oci|hybrid cloud|multi-cloud|cloud native|cloud transformation | C14: =LEN(B14)-LEN(SUBSTITUTE(B14,"|",""))+1 -> 11 | D14: Tier 2 | E14: AI
... A62: SaaS / B2B product | B62: saas|b2b|b2c|b2b2c|enterprise software|platform|api product|paas|subscription|freemium|self-serve|plg|product-led growth | C62: =LEN(B62)-LEN(SUBSTITUTE(B62,"|",""))+1 -> 13 | D62: Tier 2 | E62: PM

Sheet FINAL_RECOMMENDATION
A1: Final Recommendation - Auto-Calculated
A3: Resume Version | B3: Final Score | C3: Match Level | D3: Notes
A4: AI Transformation Manager | B4: =AI_SCORE!D26 -> 17 | C4: =IF(B4>=32,"Strong Match",IF(B4>=25,"Good Match",IF(B4>=18,"Moderate Match","Weak Match"))) -> Weak Match | D4: Best for AI/transformation-led roles, GenAI strategy, intelligent automation
A5: Technical Program Manager | B5: =TPM_SCORE!D26 -> 22 | C5: =IF(B5>=32,"Strong Match",IF(B5>=25,"Good Match",IF(B5>=18,"Moderate Match","Weak Match"))) -> Moderate Match | D5: Best for cross-functional technical delivery, program governance, roadmap execution
A6: IT Delivery Manager | B6: =ITDM_SCORE!D26 -> 9 | C6: =IF(B6>=32,"Strong Match",IF(B6>=25,"Good Match",IF(B6>=18,"Moderate Match","Weak Match"))) -> Weak Match | D6: Best for service delivery, SLA management, ITIL/ServiceNow operations
A7: Product Manager | B7: =PM_SCORE!D26 -> 16 | C7: =IF(B7>=32,"Strong Match",IF(B7>=25,"Good Match",IF(B7>=18,"Moderate Match","Weak Match"))) -> Weak Match | D7: Best for product strategy, roadmapping, feature discovery, GTM, customer metrics
A8: BEST FIT RESUME
A9: BEST FIT RESUME
A10: =INDEX(A4:A7,MATCH(MAX(B4:B7),B4:B7,0)) -> Technical Program Manager
A11: Recommended Cover Letter
A12: Recommended Cover Letter
A13: =IF(A10="AI Transformation Manager","Use: AI Transformation Manager Cover Letter - https://www.genspark.ai/api/files/s/lkUPzCNe",IF(A10="Technical Program Manager","Use: Technical Program Manager Cover Letter - https://www.genspark.ai/api/files/s/PxGCoBuk",IF(A10="IT Delivery Manager","Use: IT Delivery Manager Cover Letter - https://www.genspark.ai/api/files/s/lPnFfxiB","Use: Product Manager Cover Letter - (Template TBD)"))) -> Use: Technical Program Manager Cover Letter - https://www.genspark.ai/api/files/s/PxGCoBuk
A14: Match Level Scoring Guide
A15: Match Level Scoring Guide | B15: Final Score >= 32 | Apply with confidence, minimal edits needed
A16: Strong Match | B16: Final Score >= 32 | Apply with confidence, minimal edits needed
A17: Good Match | B17: Final Score 25-31 | Good candidate, tailor a few bullets
A18: Moderate Match | B18: Final Score 18-24 | Apply only with significant tailoring
A19: Weak Match | B19: Final Score < 18 | Consider not applying or reposition heavily
A20: Action Items Before Applying
A21: Action Items Before Applying | B21: Best-fit resume identified above. Review the matching scoring sheet column E to see which keywords were detected and which were missed.
A22: Key Gaps to Address | B22: Best-fit resume identified above. Review the matching scoring sheet column E and Top Missing Keywords table to see exact gaps.
A23: Top 5 Resume Edits | B23: 1) Mirror the top 5 JD keywords in your Professional Summary. 2) Add 1 bullet quantifying impact for the top keyword. 3) Move best-matching role experience to the top. 4) Re-title resume header to match JD role title. 5) Add JD industry or domain reference in your summary.
A25: Best Cover Letter to Use | B25: =A9&" - matching cover letter" -> BEST FIT RESUME - matching cover letter
A26: Best Cover Letter to Use | B26: =A10&" - matching cover letter" -> Technical Program Manager - matching cover letter
A27: Interview Themes to Prepare | B27: =A10&" interview prep: align your strongest stories to the top-scoring keywords on the matching scoring sheet. Prepare STAR examples for change management, governance, and one role-specific theme." -> Technical Program Manager interview prep: align your strongest stories to the top-scoring keywords on the matching scoring sheet. Prepare STAR examples for change management, governance, and one role-specific theme.
A30: Auto-Scoring Active - Edit JD_INPUT cell B10 to update all scores instantly across all 4 tracks.
A33: Dimension | B33: AI Transformation | C33: Technical PM | D33: IT Delivery | E33: Product Manager
A34: Keyword Coverage | B34: =AI_SCORE!D19 -> 12 | C34: =TPM_SCORE!D19 -> 16 | D34: =ITDM_SCORE!D19 -> 6 | E34: =PM_SCORE!D19 -> 12
A35: Pattern Match | B35: =AI_SCORE!D22 -> 1 | C35: =TPM_SCORE!D22 -> 3 | D35: =ITDM_SCORE!D22 -> 1 | E35: =PM_SCORE!D22 -> 3
A36: Company Fit | B36: =AI_SCORE!D23 -> 4 | C36: =TPM_SCORE!D23 -> 3 | D36: =ITDM_SCORE!D23 -> 2 | E36: =PM_SCORE!D23 -> 1
A37: Red Flag (inverted) | B37: =5-AI_SCORE!D24 -> 5 | C37: =5-TPM_SCORE!D24 -> 5 | D37: =5-ITDM_SCORE!D24 -> 5 | E37: =5-PM_SCORE!D24 -> 5
A38: Final Score | B38: =AI_SCORE!D26 -> 17 | C38: =TPM_SCORE!D26 -> 22 | D38: =ITDM_SCORE!D26 -> 9 | E38: =PM_SCORE!D26 -> 16

Sheet BULLET_GENERATOR
A1: ✍️ RESUME BULLET GENERATOR — Pre-written bullets you can copy into your resume
A2: =IF(LEN(JD_INPUT!B10)<50,"⏳ Paste a JD in JD_INPUT!B10 — recommended bullets will highlight below in green","✅ JD analyzed — GREEN bullets below match your JD's keywords → copy them straight into your resume") -> ✅ JD analyzed — GREEN bullets below match your JD's keywords → copy them straight into your resume
A3: Track | B3: Keyword Theme | C3: Suggested Resume Bullet (edit with your metrics) | D3: JD Hit? | E3: Recommended?
A4: 🤖 AI | B4: AI transformation | C4: Led enterprise AI transformation across [X] business units — delivered [$XM] in productivity gains and reduced manual effort by [X]% through GenAI-driven workflows. | D4: =IF(AI_SCORE!C4>=1,"✅ YES","❌ No") -> ❌ No | E4: =IF(AI_SCORE!C4>=1,"🟢 USE THIS","—") -> —
A5: 🤖 AI | B5: Digital transformation | C5: Directed digital transformation program spanning [X] applications and [X] users — modernized legacy platforms and achieved [X]% reduction in operational cost within [X] months. | D5: =IF(AI_SCORE!C5>=1,"✅ YES","❌ No") -> ❌ No | E5: =IF(AI_SCORE!C5>=1,"🟢 USE THIS","—") -> —
A6: 🤖 AI | B6: Generative AI / GenAI | C6: Architected GenAI/LLM solution using [OpenAI/Claude/Gemini] with RAG pipeline — reduced content creation time by [X]% and improved customer response accuracy by [X]%. | D6: =IF(AI_SCORE!C6>=1,"✅ YES","❌ No") -> ❌ No | E6: =IF(AI_SCORE!C6>=1,"🟢 USE THIS","—") -> —
A7: 🤖 AI | B7: Intelligent automation | C7: Deployed intelligent automation (RPA + AI) across [X] business processes — automated [X] manual workflows, saving [X] FTE hours annually. | D7: =IF(AI_SCORE!C7>=1,"✅ YES","❌ No") -> ❌ No | E7: =IF(AI_SCORE!C7>=1,"🟢 USE THIS","—") -> —
A8: 🤖 AI | B8: AI adoption / AI strategy | C8: Defined enterprise AI strategy and roadmap in partnership with C-suite — established AI Center of Excellence and governed [X]+ AI initiatives across [X] departments. | D8: =IF(AI_SCORE!C8>=1,"✅ YES","❌ No") -> ❌ No | E8: =IF(AI_SCORE!C8>=1,"🟢 USE THIS","—") -> —
A9: 🤖 AI | B9: Transformation roadmap | C9: Built multi-year transformation roadmap aligning [X] workstreams with target operating model — secured [$XM] budget and achieved [X]% milestone completion on schedule. | D9: =IF(AI_SCORE!C9>=1,"✅ YES","❌ No") -> ❌ No | E9: =IF(AI_SCORE!C9>=1,"🟢 USE THIS","—") -> —
A10: 🤖 AI | B10: Enterprise modernization | C10: Modernized [X] legacy applications to cloud-native architecture — reduced technical debt by [X]% and improved system availability from [X]% to [X]%. | D10: =IF(AI_SCORE!C10>=1,"✅ YES","❌ No") -> ❌ No | E10: =IF(AI_SCORE!C10>=1,"🟢 USE THIS","—") -> —
A11: 🤖 AI | B11: Change management | C11: Led change management for [X] transformation initiatives affecting [X]+ employees — achieved [X]% adoption rate through structured communication, training, and Prosci/ADKAR framework. | D11: =IF(AI_SCORE!C11>=1,"✅ YES","❌ No") -> ✅ YES | E11: =IF(AI_SCORE!C11>=1,"🟢 USE THIS","—") -> 🟢 USE THIS
A12: 🤖 AI | B12: Stakeholder governance | C12: Established governance framework with [X] executive steering committees — drove alignment across [X] business units and accelerated decision-making by [X]%. | D12: =IF(AI_SCORE!C12>=1,"✅ YES","❌ No") -> ✅ YES | E12: =IF(AI_SCORE!C12>=1,"🟢 USE THIS","—") -> 🟢 USE THIS
A13: 🤖 AI | B13: CRM transformation | C13: Led CRM transformation (Salesforce/Dynamics) for [X] users — consolidated [X] legacy systems, improved sales productivity by [X]%, and boosted customer NPS by [X] points. | D13: =IF(AI_SCORE!C13>=1,"✅ YES","❌ No") -> ❌ No | E13: =IF(AI_SCORE!C13>=1,"🟢 USE THIS","—") -> —
A14: 🤖 AI | B14: Salesforce / ServiceNow | C14: Managed Salesforce/ServiceNow platform delivery across [X] instances — implemented [X] custom apps and achieved [X]% user adoption within [X] months of go-live. | D14: =IF(AI_SCORE!C14>=1,"✅ YES","❌ No") -> ❌ No | E14: =IF(AI_SCORE!C14>=1,"🟢 USE THIS","—") -> —
A15: 🤖 AI | B15: Cloud migration | C15: Led cloud migration of [X] applications to [AWS/Azure/GCP] — reduced infrastructure cost by [X]%, improved deployment velocity [X]×, and completed [X] months ahead of plan. | D15: =IF(AI_SCORE!C15>=1,"✅ YES","❌ No") -> ❌ No | E15: =IF(AI_SCORE!C15>=1,"🟢 USE THIS","—") -> —
... A18: 🤖 AI | B18: Cross-functional leadership | C18: Led cross-functional teams of [X]+ across engineering, product, design, and business — delivered [X] initiatives on schedule with [X]% stakeholder satisfaction. | D18: =IF(AI_SCORE!C18>=1,"✅ YES","❌ No") -> ✅ YES | E18: =IF(AI_SCORE!C18>=1,"🟢 USE THIS","—") -> 🟢 USE THIS
A19: ⚙️ TPM | B19: Technical program management | C19: Managed [X] concurrent technical programs valued at [$XM] — coordinated [X]+ engineering teams and delivered [X]% on-time milestone completion. | D19: =IF(TPM_SCORE!C4>=1,"✅ YES","❌ No") -> ❌ No | E19: =IF(TPM_SCORE!C4>=1,"🟢 USE THIS","—") -> —
A20: ⚙️ TPM | B20: Program delivery | C20: Delivered [X] multi-quarter programs from initiation through launch — met [X]% of scope, budget, and schedule targets across [X] product releases. | D20: =IF(TPM_SCORE!C5>=1,"✅ YES","❌ No") -> ❌ No | E20: =IF(TPM_SCORE!C5>=1,"🟢 USE THIS","—") -> —
A21: ⚙️ TPM | B21: Roadmap execution | C21: Owned quarterly roadmap for [X] product areas — defined [X] OKRs, tracked [X] milestones, and delivered [X]% of committed scope per quarter. | D21: =IF(TPM_SCORE!C6>=1,"✅ YES","❌ No") -> ✅ YES | E21: =IF(TPM_SCORE!C6>=1,"🟢 USE THIS","—") -> 🟢 USE THIS
A22: ⚙️ TPM | B22: Cross-functional leadership | C22: Coordinated [X]+ engineering, product, and design teams across [X] time zones — resolved [X] critical blockers and accelerated delivery by [X] weeks. | D22: =IF(TPM_SCORE!C7>=1,"✅ YES","❌ No") -> ✅ YES | E22: =IF(TPM_SCORE!C7>=1,"🟢 USE THIS","—") -> 🟢 USE THIS
A23: ⚙️ TPM | B23: Stakeholder management | C23: Managed executive stakeholders including [VPs/Directors] across [X] business units — delivered weekly status readouts and drove alignment on [X] critical decisions. | D23: =IF(TPM_SCORE!C8>=1,"✅ YES","❌ No") -> ✅ YES | E23: =IF(TPM_SCORE!C8>=1,"🟢 USE THIS","—") -> 🟢 USE THIS
A24: ⚙️ TPM | B24: Risk management | C24: Maintained active RAID log with [X]+ risks/issues per program — mitigated [X] critical risks pre-launch and prevented [X] production incidents. | D24: =IF(TPM_SCORE!C9>=1,"✅ YES","❌ No") -> ❌ No | E24: =IF(TPM_SCORE!C9>=1,"🟢 USE THIS","—") -> —
A25: ⚙️ TPM | B25: Dependency management | C25: Tracked [X]+ inter-team dependencies across [X] engineering orgs — proactively unblocked [X] critical-path items and reduced schedule slippage by [X]%. | D25: =IF(TPM_SCORE!C10>=1,"✅ YES","❌ No") -> ✅ YES | E25: =IF(TPM_SCORE!C10>=1,"🟢 USE THIS","—") -> 🟢 USE THIS
A26: ⚙️ TPM | B26: Change management (TPM) | C26: Chaired Change Advisory Board (CAB) reviewing [X] change requests weekly — approved [X] releases with zero rollback events over [X] months. | D26: =IF(TPM_SCORE!C11>=1,"✅ YES","❌ No") -> ❌ No | E26: =IF(TPM_SCORE!C11>=1,"🟢 USE THIS","—") -> —
A27: ⚙️ TPM | B27: Release management | C27: Managed [X] production releases across [X] services — established release train cadence and achieved [X]% deployment success rate. | D27: =IF(TPM_SCORE!C12>=1,"✅ YES","❌ No") -> ❌ No | E27: =IF(TPM_SCORE!C12>=1,"🟢 USE THIS","—") -> —
A28: ⚙️ TPM | B28: SDLC / Agile / Scrum | C28: Championed Agile/Scrum practices across [X] teams — facilitated [X] sprints, drove [X]% velocity improvement, and coached [X] Scrum Masters. | D28: =IF(TPM_SCORE!C13>=1,"✅ YES","❌ No") -> ✅ YES | E28: =IF(TPM_SCORE!C13>=1,"🟢 USE THIS","—") -> 🟢 USE THIS
A29: ⚙️ TPM | B29: Enterprise systems | C29: Managed enterprise platform programs (ERP/SAP/Oracle) impacting [X] users — delivered [X] modules on time and reduced total cost of ownership by [X]%. | D29: =IF(TPM_SCORE!C14>=1,"✅ YES","❌ No") -> ✅ YES | E29: =IF(TPM_SCORE!C14>=1,"🟢 USE THIS","—") -> 🟢 USE THIS
A30: ⚙️ TPM | B30: Cloud migration (TPM) | C30: Program-managed cloud migration of [X] workloads to [AWS/Azure/GCP] — coordinated [X] teams, retired [X] legacy systems, and cut infra spend by [X]%. | D30: =IF(TPM_SCORE!C15>=1,"✅ YES","❌ No") -> ❌ No | E30: =IF(TPM_SCORE!C15>=1,"🟢 USE THIS","—") -> —
... A33: ⚙️ TPM | B33: Vendor management | C33: Managed [X] strategic vendors with combined [$XM] spend — negotiated SOWs, tracked SLA compliance, and achieved [X]% cost savings on renewal. | D33: =IF(TPM_SCORE!C18>=1,"✅ YES","❌ No") -> ❌ No | E33: =IF(TPM_SCORE!C18>=1,"🟢 USE THIS","—") -> —
A34: 🛠️ ITDM | B34: IT delivery management | C34: Led IT delivery for [X] business-critical applications across [X]+ users — met [X]% of SLA targets and reduced production incidents by [X]%. | D34: =IF(ITDM_SCORE!C4>=1,"✅ YES","❌ No") -> ❌ No | E34: =IF(ITDM_SCORE!C4>=1,"🟢 USE THIS","—") -> —
A35: 🛠️ ITDM | B35: Service delivery | C35: Owned end-to-end service delivery for [X] managed services — achieved [X]% customer satisfaction (CSAT) and reduced tickets by [X]% YoY. | D35: =IF(ITDM_SCORE!C5>=1,"✅ YES","❌ No") -> ❌ No | E35: =IF(ITDM_SCORE!C5>=1,"🟢 USE THIS","—") -> —
A36: 🛠️ ITDM | B36: SLA management | C36: Governed SLA compliance across [X] services — achieved [X]% adherence to response and resolution SLAs, avoiding [$XK] in service credit penalties. | D36: =IF(ITDM_SCORE!C6>=1,"✅ YES","❌ No") -> ✅ YES | E36: =IF(ITDM_SCORE!C6>=1,"🟢 USE THIS","—") -> 🟢 USE THIS
A37: 🛠️ ITDM | B37: Incident management | C37: Led major-incident (P1/P2) response for [X] critical outages — reduced MTTR from [X] to [X] minutes and drove postmortem/RCA to closure within [X] hours. | D37: =IF(ITDM_SCORE!C7>=1,"✅ YES","❌ No") -> ❌ No | E37: =IF(ITDM_SCORE!C7>=1,"🟢 USE THIS","—") -> —
A38: 🛠️ ITDM | B38: Problem management | C38: Drove problem management program — identified [X] recurring incidents, delivered [X] permanent fixes, and reduced repeat P1 volume by [X]%. | D38: =IF(ITDM_SCORE!C8>=1,"✅ YES","❌ No") -> ❌ No | E38: =IF(ITDM_SCORE!C8>=1,"🟢 USE THIS","—") -> —
A39: 🛠️ ITDM | B39: Change management (ITDM) | C39: Chaired weekly CAB for [X] change requests — approved [X] releases with [X]% success rate and zero unplanned rollbacks. | D39: =IF(ITDM_SCORE!C9>=1,"✅ YES","❌ No") -> ❌ No | E39: =IF(ITDM_SCORE!C9>=1,"🟢 USE THIS","—") -> —
A40: 🛠️ ITDM | B40: Release management | C40: Coordinated [X] production releases per quarter across [X] applications — achieved [X]% first-time success rate and zero SEV1 incidents post-deployment. | D40: =IF(ITDM_SCORE!C10>=1,"✅ YES","❌ No") -> ❌ No | E40: =IF(ITDM_SCORE!C10>=1,"🟢 USE THIS","—") -> —
A41: 🛠️ ITDM | B41: ITIL | C41: Implemented ITIL v4 practices across [X] service management functions — improved service ticket handling by [X]% and passed [X] ISO 20000/audit reviews. | D41: =IF(ITDM_SCORE!C11>=1,"✅ YES","❌ No") -> ❌ No | E41: =IF(ITDM_SCORE!C11>=1,"🟢 USE THIS","—") -> —
A42: 🛠️ ITDM | B42: ServiceNow | C42: Led ServiceNow platform implementation/expansion — configured [X] workflows (ITSM/ITOM/ITBM), automated [X] processes, and improved fulfillment speed by [X]%. | D42: =IF(ITDM_SCORE!C12>=1,"✅ YES","❌ No") -> ❌ No | E42: =IF(ITDM_SCORE!C12>=1,"🟢 USE THIS","—") -> —
A43: 🛠️ ITDM | B43: Operations management | C43: Directed 24×7 IT operations spanning [X] applications and [X]+ users — maintained [X]% availability and led [X]-person operations team. | D43: =IF(ITDM_SCORE!C13>=1,"✅ YES","❌ No") -> ❌ No | E43: =IF(ITDM_SCORE!C13>=1,"🟢 USE THIS","—") -> —
A44: 🛠️ ITDM | B44: Production support | C44: Ran L2/L3 production support for [X] mission-critical applications — resolved [X]+ tickets/month with [X]% within SLA and [X]% first-call resolution. | D44: =IF(ITDM_SCORE!C14>=1,"✅ YES","❌ No") -> ❌ No | E44: =IF(ITDM_SCORE!C14>=1,"🟢 USE THIS","—") -> —
A45: 🛠️ ITDM | B45: Platform availability / uptime | C45: Maintained platform availability of [X]% (99.9%+) across [X] services — implemented resilience patterns and reduced unplanned downtime by [X] hours/year. | D45: =IF(ITDM_SCORE!C15>=1,"✅ YES","❌ No") -> ✅ YES | E45: =IF(ITDM_SCORE!C15>=1,"🟢 USE THIS","—") -> 🟢 USE THIS
... A48: 🛠️ ITDM | B48: CRM support / cloud operations | C48: Managed CloudOps/CRM support for [X] production instances (Salesforce/Siebel) — sustained [X]% platform uptime and reduced escalations by [X]%. | D48: =IF(ITDM_SCORE!C18>=1,"✅ YES","❌ No") -> ❌ No | E48: =IF(ITDM_SCORE!C18>=1,"🟢 USE THIS","—") -> —
A49: 📦 PM | B49: Product management | C49: Owned end-to-end product lifecycle for [Product/Platform], driving [X]% increase in monthly active users and generating [$XM] in annualized recurring revenue. | D49: =IF(PM_SCORE!C4>=1,"✅ YES","❌ No") -> ❌ No | E49: =IF(PM_SCORE!C4>=1,"🟢 USE THIS","—") -> —
A50: 📦 PM | B50: Product strategy | C50: Defined 3-year product vision and strategic north star metrics across [X] customer segments, aligning [X] executive stakeholders on multi-quarter roadmaps. | D50: =IF(PM_SCORE!C5>=1,"✅ YES","❌ No") -> ❌ No | E50: =IF(PM_SCORE!C5>=1,"🟢 USE THIS","—") -> —
A51: 📦 PM | B51: Product roadmap | C51: Constructed outcome-driven product roadmap balancing tech debt with feature velocity, achieving [X]% on-time milestone delivery across [X] quarterly releases. | D51: =IF(PM_SCORE!C6>=1,"✅ YES","❌ No") -> ✅ YES | E51: =IF(PM_SCORE!C6>=1,"🟢 USE THIS","—") -> 🟢 USE THIS
A52: 📦 PM | B52: Customer discovery | C52: Conducted [X]+ customer discovery interviews and synthesized Voice of Customer (VoC) feedback into high-priority backlog epics, boosting NPS by [X] pts. | D52: =IF(PM_SCORE!C7>=1,"✅ YES","❌ No") -> ❌ No | E52: =IF(PM_SCORE!C7>=1,"🟢 USE THIS","—") -> —
A53: 📦 PM | B53: User research | C53: Partnered with UX research to run [X] usability testing cycles, reducing customer onboarding friction and lowering time-to-first-value by [X]%. | D53: =IF(PM_SCORE!C8>=1,"✅ YES","❌ No") -> ❌ No | E53: =IF(PM_SCORE!C8>=1,"🟢 USE THIS","—") -> —
A54: 📦 PM | B54: Product analytics | C54: Built granular product telemetry in [Amplitude/Mixpanel/FullStory], identifying drop-off bottlenecks and improving core conversion funnel by [X]%. | D54: =IF(PM_SCORE!C9>=1,"✅ YES","❌ No") -> ❌ No | E54: =IF(PM_SCORE!C9>=1,"🟢 USE THIS","—") -> —
A55: 📦 PM | B55: A/B testing / experimentation | C55: Designed and executed [X]+ A/B experiments on pricing/packaging and feature activation, delivering a statistically significant [X]% lift in trial-to-paid conversion. | D55: =IF(PM_SCORE!C10>=1,"✅ YES","❌ No") -> ❌ No | E55: =IF(PM_SCORE!C10>=1,"🟢 USE THIS","—") -> —
A56: 📦 PM | B56: Product-market fit | C56: Identified high-growth ICP and accelerated product-market fit (PMF), scaling DAU/MAU ratio from [X]% to [X]% and reducing customer churn by [X]%. | D56: =IF(PM_SCORE!C11>=1,"✅ YES","❌ No") -> ❌ No | E56: =IF(PM_SCORE!C11>=1,"🟢 USE THIS","—") -> —
A57: 📦 PM | B57: Product launch / GTM | C57: Led cross-functional GTM launch for [Feature/Product], training [X] sales/CS reps, acquiring [X]+ beta users in week 1, and exceeding pipeline target by [X]%. | D57: =IF(PM_SCORE!C12>=1,"✅ YES","❌ No") -> ✅ YES | E57: =IF(PM_SCORE!C12>=1,"🟢 USE THIS","—") -> 🟢 USE THIS
A58: 📦 PM | B58: Stakeholder management PM | C58: Managed executive alignment across Sales, Marketing, CS, and Engineering, securing buy-in for [X] tier-1 product initiatives. | D58: =IF(PM_SCORE!C13>=1,"✅ YES","❌ No") -> ❌ No | E58: =IF(PM_SCORE!C13>=1,"🟢 USE THIS","—") -> —
A59: 📦 PM | B59: Cross-functional leadership PM | C59: Led squad of [X] engineers, designers, and data analysts in agile cadence; maintained high team morale and improved velocity by [X]%. | D59: =IF(PM_SCORE!C14>=1,"✅ YES","❌ No") -> ✅ YES | E59: =IF(PM_SCORE!C14>=1,"🟢 USE THIS","—") -> 🟢 USE THIS
A60: 📦 PM | B60: Data-driven decisions | C60: Established quantitative decision frameworks prioritizing features by expected ROI, customer impact, and engineering feasibility. | D60: =IF(PM_SCORE!C15>=1,"✅ YES","❌ No") -> ❌ No | E60: =IF(PM_SCORE!C15>=1,"🟢 USE THIS","—") -> —
... A63: 📦 PM | B63: SaaS / B2B product | C63: Scaled enterprise B2B SaaS platform serving [X]+ enterprise logos, implementing self-serve PLG motions alongside high-touch enterprise workflows. | D63: =IF(PM_SCORE!C18>=1,"✅ YES","❌ No") -> ✅ YES | E63: =IF(PM_SCORE!C18>=1,"🟢 USE THIS","—") -> 🟢 USE THIS
A65: 📊 Total Recommended Bullets | B65: =COUNTIF(E4:E63,"🟢 USE THIS")&" bullets are green-flagged and ready to copy into your resume (out of 60 total)." -> 20 bullets are green-flagged and ready to copy into your resume (out of 60 total). | D65: =IF(LEN(JD_INPUT!B10)<50,"⏳ Waiting","✅ Ready") -> ✅ Ready | E65: =JD_INPUT!B25 -> Technical Program Manager
